Workbook
Name MAP_TABLE: 内部_リスト!$C$2:$D$20
Name RESPX_001: 内部_リスト!$F$2:$F$4
Name RESPX_002: 内部_リスト!$G$2:$G$5
Name RESPX_003: 内部_リスト!$H$2:$H$5
Name RESPX_004: 内部_リスト!$I$2:$I$4
Name RESPX_005: 内部_リスト!$J$2:$J$3
Name RESPX_006: 内部_リスト!$K$2:$K$3
Name RESPX_007: 内部_リスト!$L$2:$L$3
Name RESPX_008: 内部_リスト!$M$2:$M$5
Name RESPX_009: 内部_リスト!$N$2:$N$3
Name RESPX_010: 内部_リスト!$O$2:$O$3
Name RESPX_011: 内部_リスト!$P$2:$P$5
Name RESPX_012: 内部_リスト!$Q$2:$Q$3
Name RESPX_013: 内部_リスト!$R$2:$R$3
Name RESPX_014: 内部_リスト!$S$2:$S$3
Name RESPX_015: 内部_リスト!$T$2:$T$2
Name RESPX_016: 内部_リスト!$U$2:$U$3
Name RESPX_017: 内部_リスト!$V$2:$V$2
Name RESPX_018: 内部_リスト!$W$2:$W$2
Name RESPX_019: 内部_リスト!$X$2:$X$2
Name STAGE_LIST: 内部_リスト!$A$2:$A$20
Name STATUS_LIST: 内部_リスト!$B$2:$B$9

Sheet 架電シート
A1: No | B1: 施設名 | C1: 電話番号 | D1: エリア | E1: 担当部署/役職 | F1: 担当者名 | G1: 現在ステージ（選択） | H1: 相手の反応（選択） | I1: 次に話す内容（自動表示） | J1: 次ステージ（自動） | K1: 結果ステータス | L1: 次回架電日時 | M1: メモ | N1: 送付先メール | O1: 最終更新 | R1: ステージ2（選択/自動） | S1: 反応2（選択） | T1: 話す内容2（自動表示） | U1: 次ステージ2（自動） | V1: ステージ3（選択/自動） | W1: 反応3（選択） | X1: 話す内容3（自動表示） | Y1: 次ステージ3（自動） | Z1: ステージ4（選択/自動） | AA1: 反応4（選択） | AB1: 話す内容4（自動表示） | AC1: 次ステージ4（自動） | AD1: ステージ5（選択/自動） | AE1: 反応5（選択） | AF1: 話す内容5（自動表示） | AG1: 次ステージ5（自動）
A2: 1 | B2: 別府温泉 杉乃井ホテル | C2: 0977-78-8888 | D2: 観海寺 | G2: ①架電 | H2: 担当者に直接繋がった | I2: =SUBSTITUTE(SUBSTITUTE(SUBSTITUTE(SUBSTITUTE(SUBSTITUTE(SUBSTITUTE(SUBSTITUTE(SUBSTITUTE(SUBSTITUTE(SUBSTITUTE(SUBSTITUTE(Q2,"{会社}",設定!$B$3),"{自分}",設定!$B$4),"{サービス}",設定!$B$5),"{料金}",設定!$B$7),"{日付1}",設定!$B$8),"{日付2}",設定!$B$9),"{時間1}",設定!$B$10),"{時間2}",設定!$B$11),"{時間}","（指定時間）"),"{日付確定}","（確定日）"),"{時間確定}","（確定時間）") -> （担当者様へ）お世話になっております。株式会社NanoActのキンタマと申します。宿泊者さま向けに「特定小型原付のシェアリング」を施設に設置するご相談でお電話しました。今1〜2分だけお時間よろしいでしょうか？ | J2: =IFERROR(VLOOKUP(P2,スクリプト_フロー!$A:$F,4,FALSE),"") -> ⑥目的伝達 | K2: 未架電 | P2: =G2&"|"&H2 -> ①架電|担当者に直接繋がった | Q2: =IFERROR(VLOOKUP(P2,スクリプト_フロー!$A:$F,5,FALSE),"") -> （担当者様へ）お世話になっております。{会社}の{自分}と申します。宿泊者さま向けに「{サービス}」を施設に設置するご相談でお電話しました。今1〜2分だけお時間よろしいでしょうか？ | T2: =IF(DA2="","",SUBSTITUTE(SUBSTITUTE(SUBSTITUTE(SUBSTITUTE(SUBSTITUTE(SUBSTITUTE(SUBSTITUTE(SUBSTITUTE(SUBSTITUTE(SUBSTITUTE(SUBSTITUTE(DA2,"{会社}",設定!$B$3),"{自分}",設定!$B$4),"{サービス}",設定!$B$5),"{料金}",設定!$B$7),"{日付1}",設定!$B$8),"{日付2}",設定!$B$9),"{時間1}",設定!$B$10),"{時間2}",設定!$B$11),"{時間}","（指定時間）"),"{日付確定}","（確定日）"),"{時間確定}","（確定時間）")) | U2: =IFERROR(VLOOKUP(CZ2,スクリプト_フロー!$A:$F,4,FALSE),"") | V2: =IF(U2="","",U2) | X2: =IF(DC2="","",SUBSTITUTE(SUBSTITUTE(SUBSTITUTE(SUBSTITUTE(SUBSTITUTE(SUBSTITUTE(SUBSTITUTE(SUBSTITUTE(SUBSTITUTE(SUBSTITUTE(SUBSTITUTE(DC2,"{会社}",設定!$B$3),"{自分}",設定!$B$4),"{サービス}",設定!$B$5),"{料金}",設定!$B$7),"{日付1}",設定!$B$8),"{日付2}",設定!$B$9),"{時間1}",設定!$B$10),"{時間2}",設定!$B$11),"{時間}","（指定時間）"),"{日付確定}","（確定日）"),"{時間確定}","（確定時間）")) | Y2: =IFERROR(VLOOKUP(DB2,スクリプト_フロー!$A:$F,4,FALSE),"") | Z2: =IF(Y2="","",Y2) | AA2: ①架電 | AB2: =IF(DE2="","",SUBSTITUTE(SUBSTITUTE(SUBSTITUTE(SUBSTITUTE(SUBSTITUTE(SUBSTITUTE(SUBSTITUTE(SUBSTITUTE(SUBSTITUTE(SUBSTITUTE(SUBSTITUTE(DE2,"{会社}",設定!$B$3),"{自分}",設定!$B$4),"{サービス}",設定!$B$5),"{料金}",設定!$B$7),"{日付1}",設定!$B$8),"{日付2}",設定!$B$9),"{時間1}",設定!$B$10),"{時間2}",設定!$B$11),"{時間}","（指定時間）"),"{日付確定}","（確定日）"),"{時間確定}","（確定時間）")) | AC2: =IFERROR(VLOOKUP(DD2,スクリプト_フロー!$A:$F,4,FALSE),"") | AD2: =IF(AC2="","",AC2) | AE2: RESPX_001 | AF2: =IF(DG2="","",SUBSTITUTE(SUBSTITUTE(SUBSTITUTE(SUBSTITUTE(SUBSTITUTE(SUBSTITUTE(SUBSTITUTE(SUBSTITUTE(SUBSTITUTE(SUBSTITUTE(SUBSTITUTE(DG2,"{会社}",設定!$B$3),"{自分}",設定!$B$4),"{サービス}",設定!$B$5),"{料金}",設定!$B$7),"{日付1}",設定!$B$8),"{日付2}",設定!$B$9),"{時間1}",設定!$B$10),"{時間2}",設定!$B$11),"{時間}","（指定時間）"),"{日付確定}","（確定日）"),"{時間確定}","（確定時間）")) | AG2: =IFERROR(VLOOKUP(DF2,スクリプト_フロー!$A:$F,4,FALSE),"") | CZ2: =R2&"|"&S2 -> | | DA2: =IFERROR(VLOOKUP(CZ2,スクリプト_フロー!$A:$F,5,FALSE),"") | DB2: =V2&"|"&W2 -> | | DC2: =IFERROR(VLOOKUP(DB2,スクリプト_フロー!$A:$F,5,FALSE),"") | DD2: =Z2&"|"&AA2 -> |①架電 | DE2: =IFERROR(VLOOKUP(DD2,スクリプト_フロー!$A:$F,5,FALSE),"") | DF2: =AD2&"|"&AE2 -> |RESPX_001 | DG2: =IFERROR(VLOOKUP(DF2,スクリプト_フロー!$A:$F,5,FALSE),"")
A3: 2 | B3: 界 別府 | C3: 050-3134-8092 | D3: 北浜 | G3: ①架電 | I3: =SUBSTITUTE(SUBSTITUTE(SUBSTITUTE(SUBSTITUTE(SUBSTITUTE(SUBSTITUTE(SUBSTITUTE(SUBSTITUTE(SUBSTITUTE(SUBSTITUTE(SUBSTITUTE(Q3,"{会社}",設定!$B$3),"{自分}",設定!$B$4),"{サービス}",設定!$B$5),"{料金}",設定!$B$7),"{日付1}",設定!$B$8),"{日付2}",設定!$B$9),"{時間1}",設定!$B$10),"{時間2}",設定!$B$11),"{時間}","（指定時間）"),"{日付確定}","（確定日）"),"{時間確定}","（確定時間）") | J3: =IFERROR(VLOOKUP(P3,スクリプト_フロー!$A:$F,4,FALSE),"") | K3: 未架電 | P3: =G3&"|"&H3 -> ①架電| | Q3: =IFERROR(VLOOKUP(P3,スクリプト_フロー!$A:$F,5,FALSE),"") | R3: =IF(J3="","",J3) | T3: =IF(DA3="","",SUBSTITUTE(SUBSTITUTE(SUBSTITUTE(SUBSTITUTE(SUBSTITUTE(SUBSTITUTE(SUBSTITUTE(SUBSTITUTE(SUBSTITUTE(SUBSTITUTE(SUBSTITUTE(DA3,"{会社}",設定!$B$3),"{自分}",設定!$B$4),"{サービス}",設定!$B$5),"{料金}",設定!$B$7),"{日付1}",設定!$B$8),"{日付2}",設定!$B$9),"{時間1}",設定!$B$10),"{時間2}",設定!$B$11),"{時間}","（指定時間）"),"{日付確定}","（確定日）"),"{時間確定}","（確定時間）")) | U3: =IFERROR(VLOOKUP(CZ3,スクリプト_フロー!$A:$F,4,FALSE),"") | V3: =IF(U3="","",U3) | X3: =IF(DC3="","",SUBSTITUTE(SUBSTITUTE(SUBSTITUTE(SUBSTITUTE(SUBSTITUTE(SUBSTITUTE(SUBSTITUTE(SUBSTITUTE(SUBSTITUTE(SUBSTITUTE(SUBSTITUTE(DC3,"{会社}",設定!$B$3),"{自分}",設定!$B$4),"{サービス}",設定!$B$5),"{料金}",設定!$B$7),"{日付1}",設定!$B$8),"{日付2}",設定!$B$9),"{時間1}",設定!$B$10),"{時間2}",設定!$B$11),"{時間}","（指定時間）"),"{日付確定}","（確定日）"),"{時間確定}","（確定時間）")) | Y3: =IFERROR(VLOOKUP(DB3,スクリプト_フロー!$A:$F,4,FALSE),"") | Z3: =IF(Y3="","",Y3) | AA3: ①-2自動音声 | AB3: =IF(DE3="","",SUBSTITUTE(SUBSTITUTE(SUBSTITUTE(SUBSTITUTE(SUBSTITUTE(SUBSTITUTE(SUBSTITUTE(SUBSTITUTE(SUBSTITUTE(SUBSTITUTE(SUBSTITUTE(DE3,"{会社}",設定!$B$3),"{自分}",設定!$B$4),"{サービス}",設定!$B$5),"{料金}",設定!$B$7),"{日付1}",設定!$B$8),"{日付2}",設定!$B$9),"{時間1}",設定!$B$10),"{時間2}",設定!$B$11),"{時間}","（指定時間）"),"{日付確定}","（確定日）"),"{時間確定}","（確定時間）")) | AC3: =IFERROR(VLOOKUP(DD3,スクリプト_フロー!$A:$F,4,FALSE),"") | AD3: =IF(AC3="","",AC3) | AE3: RESPX_002 | AF3: =IF(DG3="","",SUBSTITUTE(SUBSTITUTE(SUBSTITUTE(SUBSTITUTE(SUBSTITUTE(SUBSTITUTE(SUBSTITUTE(SUBSTITUTE(SUBSTITUTE(SUBSTITUTE(SUBSTITUTE(DG3,"{会社}",設定!$B$3),"{自分}",設定!$B$4),"{サービス}",設定!$B$5),"{料金}",設定!$B$7),"{日付1}",設定!$B$8),"{日付2}",設定!$B$9),"{時間1}",設定!$B$10),"{時間2}",設定!$B$11),"{時間}","（指定時間）"),"{日付確定}","（確定日）"),"{時間確定}","（確定時間）")) | AG3: =IFERROR(VLOOKUP(DF3,スクリプト_フロー!$A:$F,4,FALSE),"") | CZ3: =R3&"|"&S3 -> | | DA3: =IFERROR(VLOOKUP(CZ3,スクリプト_フロー!$A:$F,5,FALSE),"") | DB3: =V3&"|"&W3 -> | | DC3: =IFERROR(VLOOKUP(DB3,スクリプト_フロー!$A:$F,5,FALSE),"") | DD3: =Z3&"|"&AA3 -> |①-2自動音声 | DE3: =IFERROR(VLOOKUP(DD3,スクリプト_フロー!$A:$F,5,FALSE),"") | DF3: =AD3&"|"&AE3 -> |RESPX_002 | DG3: =IFERROR(VLOOKUP(DF3,スクリプト_フロー!$A:$F,5,FALSE),"")
A4: 3 | B4: 亀の井ホテル 別府 | C4: 0977-22-3301 | D4: 別府駅周辺 | G4: ①架電 | I4: =SUBSTITUTE(SUBSTITUTE(SUBSTITUTE(SUBSTITUTE(SUBSTITUTE(SUBSTITUTE(SUBSTITUTE(SUBSTITUTE(SUBSTITUTE(SUBSTITUTE(SUBSTITUTE(Q4,"{会社}",設定!$B$3),"{自分}",設定!$B$4),"{サービス}",設定!$B$5),"{料金}",設定!$B$7),"{日付1}",設定!$B$8),"{日付2}",設定!$B$9),"{時間1}",設定!$B$10),"{時間2}",設定!$B$11),"{時間}","（指定時間）"),"{日付確定}","（確定日）"),"{時間確定}","（確定時間）") | J4: =IFERROR(VLOOKUP(P4,スクリプト_フロー!$A:$F,4,FALSE),"") | K4: 未架電 | P4: =G4&"|"&H4 -> ①架電| | Q4: =IFERROR(VLOOKUP(P4,スクリプト_フロー!$A:$F,5,FALSE),"") | R4: =IF(J4="","",J4) | T4: =IF(DA4="","",SUBSTITUTE(SUBSTITUTE(SUBSTITUTE(SUBSTITUTE(SUBSTITUTE(SUBSTITUTE(SUBSTITUTE(SUBSTITUTE(SUBSTITUTE(SUBSTITUTE(SUBSTITUTE(DA4,"{会社}",設定!$B$3),"{自分}",設定!$B$4),"{サービス}",設定!$B$5),"{料金}",設定!$B$7),"{日付1}",設定!$B$8),"{日付2}",設定!$B$9),"{時間1}",設定!$B$10),"{時間2}",設定!$B$11),"{時間}","（指定時間）"),"{日付確定}","（確定日）"),"{時間確定}","（確定時間）")) | U4: =IFERROR(VLOOKUP(CZ4,スクリプト_フロー!$A:$F,4,FALSE),"") | V4: =IF(U4="","",U4) | X4: =IF(DC4="","",SUBSTITUTE(SUBSTITUTE(SUBSTITUTE(SUBSTITUTE(SUBSTITUTE(SUBSTITUTE(SUBSTITUTE(SUBSTITUTE(SUBSTITUTE(SUBSTITUTE(SUBSTITUTE(DC4,"{会社}",設定!$B$3),"{自分}",設定!$B$4),"{サービス}",設定!$B$5),"{料金}",設定!$B$7),"{日付1}",設定!$B$8),"{日付2}",設定!$B$9),"{時間1}",設定!$B$10),"{時間2}",設定!$B$11),"{時間}","（指定時間）"),"{日付確定}","（確定日）"),"{時間確定}","（確定時間）")) | Y4: =IFERROR(VLOOKUP(DB4,スクリプト_フロー!$A:$F,4,FALSE),"") | Z4: =IF(Y4="","",Y4) | AA4: ②受付 | AB4: =IF(DE4="","",SUBSTITUTE(SUBSTITUTE(SUBSTITUTE(SUBSTITUTE(SUBSTITUTE(SUBSTITUTE(SUBSTITUTE(SUBSTITUTE(SUBSTITUTE(SUBSTITUTE(SUBSTITUTE(DE4,"{会社}",設定!$B$3),"{自分}",設定!$B$4),"{サービス}",設定!$B$5),"{料金}",設定!$B$7),"{日付1}",設定!$B$8),"{日付2}",設定!$B$9),"{時間1}",設定!$B$10),"{時間2}",設定!$B$11),"{時間}","（指定時間）"),"{日付確定}","（確定日）"),"{時間確定}","（確定時間）")) | AC4: =IFERROR(VLOOKUP(DD4,スクリプト_フロー!$A:$F,4,FALSE),"") | AD4: =IF(AC4="","",AC4) | AE4: RESPX_003 | AF4: =IF(DG4="","",SUBSTITUTE(SUBSTITUTE(SUBSTITUTE(SUBSTITUTE(SUBSTITUTE(SUBSTITUTE(SUBSTITUTE(SUBSTITUTE(SUBSTITUTE(SUBSTITUTE(SUBSTITUTE(DG4,"{会社}",設定!$B$3),"{自分}",設定!$B$4),"{サービス}",設定!$B$5),"{料金}",設定!$B$7),"{日付1}",設定!$B$8),"{日付2}",設定!$B$9),"{時間1}",設定!$B$10),"{時間2}",設定!$B$11),"{時間}","（指定時間）"),"{日付確定}","（確定日）"),"{時間確定}","（確定時間）")) | AG4: =IFERROR(VLOOKUP(DF4,スクリプト_フロー!$A:$F,4,FALSE),"") | CZ4: =R4&"|"&S4 -> | | DA4: =IFERROR(VLOOKUP(CZ4,スクリプト_フロー!$A:$F,5,FALSE),"") | DB4: =V4&"|"&W4 -> | | DC4: =IFERROR(VLOOKUP(DB4,スクリプト_フロー!$A:$F,5,FALSE),"") | DD4: =Z4&"|"&AA4 -> |②受付 | DE4: =IFERROR(VLOOKUP(DD4,スクリプト_フロー!$A:$F,5,FALSE),"") | DF4: =AD4&"|"&AE4 -> |RESPX_003 | DG4: =IFERROR(VLOOKUP(DF4,スクリプト_フロー!$A:$F,5,FALSE),"")
A5: 4 | B5: 西鉄リゾートイン別府 | C5: 0977-26-5151 | D5: 北浜 | G5: ①架電 | I5: =SUBSTITUTE(SUBSTITUTE(SUBSTITUTE(SUBSTITUTE(SUBSTITUTE(SUBSTITUTE(SUBSTITUTE(SUBSTITUTE(SUBSTITUTE(SUBSTITUTE(SUBSTITUTE(Q5,"{会社}",設定!$B$3),"{自分}",設定!$B$4),"{サービス}",設定!$B$5),"{料金}",設定!$B$7),"{日付1}",設定!$B$8),"{日付2}",設定!$B$9),"{時間1}",設定!$B$10),"{時間2}",設定!$B$11),"{時間}","（指定時間）"),"{日付確定}","（確定日）"),"{時間確定}","（確定時間）") | J5: =IFERROR(VLOOKUP(P5,スクリプト_フロー!$A:$F,4,FALSE),"") | K5: 未架電 | P5: =G5&"|"&H5 -> ①架電| | Q5: =IFERROR(VLOOKUP(P5,スクリプト_フロー!$A:$F,5,FALSE),"") | R5: =IF(J5="","",J5) | T5: =IF(DA5="","",SUBSTITUTE(SUBSTITUTE(SUBSTITUTE(SUBSTITUTE(SUBSTITUTE(SUBSTITUTE(SUBSTITUTE(SUBSTITUTE(SUBSTITUTE(SUBSTITUTE(SUBSTITUTE(DA5,"{会社}",設定!$B$3),"{自分}",設定!$B$4),"{サービス}",設定!$B$5),"{料金}",設定!$B$7),"{日付1}",設定!$B$8),"{日付2}",設定!$B$9),"{時間1}",設定!$B$10),"{時間2}",設定!$B$11),"{時間}","（指定時間）"),"{日付確定}","（確定日）"),"{時間確定}","（確定時間）")) | U5: =IFERROR(VLOOKUP(CZ5,スクリプト_フロー!$A:$F,4,FALSE),"") | V5: =IF(U5="","",U5) | X5: =IF(DC5="","",SUBSTITUTE(SUBSTITUTE(SUBSTITUTE(SUBSTITUTE(SUBSTITUTE(SUBSTITUTE(SUBSTITUTE(SUBSTITUTE(SUBSTITUTE(SUBSTITUTE(SUBSTITUTE(DC5,"{会社}",設定!$B$3),"{自分}",設定!$B$4),"{サービス}",設定!$B$5),"{料金}",設定!$B$7),"{日付1}",設定!$B$8),"{日付2}",設定!$B$9),"{時間1}",設定!$B$10),"{時間2}",設定!$B$11),"{時間}","（指定時間）"),"{日付確定}","（確定日）"),"{時間確定}","（確定時間）")) | Y5: =IFERROR(VLOOKUP(DB5,スクリプト_フロー!$A:$F,4,FALSE),"") | Z5: =IF(Y5="","",Y5) | AA5: ③受付用件 | AB5: =IF(DE5="","",SUBSTITUTE(SUBSTITUTE(SUBSTITUTE(SUBSTITUTE(SUBSTITUTE(SUBSTITUTE(SUBSTITUTE(SUBSTITUTE(SUBSTITUTE(SUBSTITUTE(SUBSTITUTE(DE5,"{会社}",設定!$B$3),"{自分}",設定!$B$4),"{サービス}",設定!$B$5),"{料金}",設定!$B$7),"{日付1}",設定!$B$8),"{日付2}",設定!$B$9),"{時間1}",設定!$B$10),"{時間2}",設定!$B$11),"{時間}","（指定時間）"),"{日付確定}","（確定日）"),"{時間確定}","（確定時間）")) | AC5: =IFERROR(VLOOKUP(DD5,スクリプト_フロー!$A:$F,4,FALSE),"") | AD5: =IF(AC5="","",AC5) | AE5: RESPX_004 | AF5: =IF(DG5="","",SUBSTITUTE(SUBSTITUTE(SUBSTITUTE(SUBSTITUTE(SUBSTITUTE(SUBSTITUTE(SUBSTITUTE(SUBSTITUTE(SUBSTITUTE(SUBSTITUTE(SUBSTITUTE(DG5,"{会社}",設定!$B$3),"{自分}",設定!$B$4),"{サービス}",設定!$B$5),"{料金}",設定!$B$7),"{日付1}",設定!$B$8),"{日付2}",設定!$B$9),"{時間1}",設定!$B$10),"{時間2}",設定!$B$11),"{時間}","（指定時間）"),"{日付確定}","（確定日）"),"{時間確定}","（確定時間）")) | AG5: =IFERROR(VLOOKUP(DF5,スクリプト_フロー!$A:$F,4,FALSE),"") | CZ5: =R5&"|"&S5 -> | | DA5: =IFERROR(VLOOKUP(CZ5,スクリプト_フロー!$A:$F,5,FALSE),"") | DB5: =V5&"|"&W5 -> | | DC5: =IFERROR(VLOOKUP(DB5,スクリプト_フロー!$A:$F,5,FALSE),"") | DD5: =Z5&"|"&AA5 -> |③受付用件 | DE5: =IFERROR(VLOOKUP(DD5,スクリプト_フロー!$A:$F,5,FALSE),"") | DF5: =AD5&"|"&AE5 -> |RESPX_004 | DG5: =IFERROR(VLOOKUP(DF5,スクリプト_フロー!$A:$F,5,FALSE),"")
A6: 5 | B6: 別府温泉 ホテル白菊 | C6: 0977-21-2111 | D6: 駅周辺 | G6: ①架電 | I6: =SUBSTITUTE(SUBSTITUTE(SUBSTITUTE(SUBSTITUTE(SUBSTITUTE(SUBSTITUTE(SUBSTITUTE(SUBSTITUTE(SUBSTITUTE(SUBSTITUTE(SUBSTITUTE(Q6,"{会社}",設定!$B$3),"{自分}",設定!$B$4),"{サービス}",設定!$B$5),"{料金}",設定!$B$7),"{日付1}",設定!$B$8),"{日付2}",設定!$B$9),"{時間1}",設定!$B$10),"{時間2}",設定!$B$11),"{時間}","（指定時間）"),"{日付確定}","（確定日）"),"{時間確定}","（確定時間）") | J6: =IFERROR(VLOOKUP(P6,スクリプト_フロー!$A:$F,4,FALSE),"") | K6: 未架電 | P6: =G6&"|"&H6 -> ①架電| | Q6: =IFERROR(VLOOKUP(P6,スクリプト_フロー!$A:$F,5,FALSE),"") | R6: =IF(J6="","",J6) | T6: =IF(DA6="","",SUBSTITUTE(SUBSTITUTE(SUBSTITUTE(SUBSTITUTE(SUBSTITUTE(SUBSTITUTE(SUBSTITUTE(SUBSTITUTE(SUBSTITUTE(SUBSTITUTE(SUBSTITUTE(DA6,"{会社}",設定!$B$3),"{自分}",設定!$B$4),"{サービス}",設定!$B$5),"{料金}",設定!$B$7),"{日付1}",設定!$B$8),"{日付2}",設定!$B$9),"{時間1}",設定!$B$10),"{時間2}",設定!$B$11),"{時間}","（指定時間）"),"{日付確定}","（確定日）"),"{時間確定}","（確定時間）")) | U6: =IFERROR(VLOOKUP(CZ6,スクリプト_フロー!$A:$F,4,FALSE),"") | V6: =IF(U6="","",U6) | X6: =IF(DC6="","",SUBSTITUTE(SUBSTITUTE(SUBSTITUTE(SUBSTITUTE(SUBSTITUTE(SUBSTITUTE(SUBSTITUTE(SUBSTITUTE(SUBSTITUTE(SUBSTITUTE(SUBSTITUTE(DC6,"{会社}",設定!$B$3),"{自分}",設定!$B$4),"{サービス}",設定!$B$5),"{料金}",設定!$B$7),"{日付1}",設定!$B$8),"{日付2}",設定!$B$9),"{時間1}",設定!$B$10),"{時間2}",設定!$B$11),"{時間}","（指定時間）"),"{日付確定}","（確定日）"),"{時間確定}","（確定時間）")) | Y6: =IFERROR(VLOOKUP(DB6,スクリプト_フロー!$A:$F,4,FALSE),"") | Z6: =IF(Y6="","",Y6) | AA6: ④不在対応 | AB6: =IF(DE6="","",SUBSTITUTE(SUBSTITUTE(SUBSTITUTE(SUBSTITUTE(SUBSTITUTE(SUBSTITUTE(SUBSTITUTE(SUBSTITUTE(SUBSTITUTE(SUBSTITUTE(SUBSTITUTE(DE6,"{会社}",設定!$B$3),"{自分}",設定!$B$4),"{サービス}",設定!$B$5),"{料金}",設定!$B$7),"{日付1}",設定!$B$8),"{日付2}",設定!$B$9),"{時間1}",設定!$B$10),"{時間2}",設定!$B$11),"{時間}","（指定時間）"),"{日付確定}","（確定日）"),"{時間確定}","（確定時間）")) | AC6: =IFERROR(VLOOKUP(DD6,スクリプト_フロー!$A:$F,4,FALSE),"") | AD6: =IF(AC6="","",AC6) | AE6: RESPX_005 | AF6: =IF(DG6="","",SUBSTITUTE(SUBSTITUTE(SUBSTITUTE(SUBSTITUTE(SUBSTITUTE(SUBSTITUTE(SUBSTITUTE(SUBSTITUTE(SUBSTITUTE(SUBSTITUTE(SUBSTITUTE(DG6,"{会社}",設定!$B$3),"{自分}",設定!$B$4),"{サービス}",設定!$B$5),"{料金}",設定!$B$7),"{日付1}",設定!$B$8),"{日付2}",設定!$B$9),"{時間1}",設定!$B$10),"{時間2}",設定!$B$11),"{時間}","（指定時間）"),"{日付確定}","（確定日）"),"{時間確定}","（確定時間）")) | AG6: =IFERROR(VLOOKUP(DF6,スクリプト_フロー!$A:$F,4,FALSE),"") | CZ6: =R6&"|"&S6 -> | | DA6: =IFERROR(VLOOKUP(CZ6,スクリプト_フロー!$A:$F,5,FALSE),"") | DB6: =V6&"|"&W6 -> | | DC6: =IFERROR(VLOOKUP(DB6,スクリプト_フロー!$A:$F,5,FALSE),"") | DD6: =Z6&"|"&AA6 -> |④不在対応 | DE6: =IFERROR(VLOOKUP(DD6,スクリプト_フロー!$A:$F,5,FALSE),"") | DF6: =AD6&"|"&AE6 -> |RESPX_005 | DG6: =IFERROR(VLOOKUP(DF6,スクリプト_フロー!$A:$F,5,FALSE),"")
A7: 6 | B7: 竹と椿のお宿 花べっぷ | C7: 0977-21-0050 | D7: 北浜 | G7: ①架電 | I7: =SUBSTITUTE(SUBSTITUTE(SUBSTITUTE(SUBSTITUTE(SUBSTITUTE(SUBSTITUTE(SUBSTITUTE(SUBSTITUTE(SUBSTITUTE(SUBSTITUTE(SUBSTITUTE(Q7,"{会社}",設定!$B$3),"{自分}",設定!$B$4),"{サービス}",設定!$B$5),"{料金}",設定!$B$7),"{日付1}",設定!$B$8),"{日付2}",設定!$B$9),"{時間1}",設定!$B$10),"{時間2}",設定!$B$11),"{時間}","（指定時間）"),"{日付確定}","（確定日）"),"{時間確定}","（確定時間）") | J7: =IFERROR(VLOOKUP(P7,スクリプト_フロー!$A:$F,4,FALSE),"") | K7: 未架電 | P7: =G7&"|"&H7 -> ①架電| | Q7: =IFERROR(VLOOKUP(P7,スクリプト_フロー!$A:$F,5,FALSE),"") | R7: =IF(J7="","",J7) | T7: =IF(DA7="","",SUBSTITUTE(SUBSTITUTE(SUBSTITUTE(SUBSTITUTE(SUBSTITUTE(SUBSTITUTE(SUBSTITUTE(SUBSTITUTE(SUBSTITUTE(SUBSTITUTE(SUBSTITUTE(DA7,"{会社}",設定!$B$3),"{自分}",設定!$B$4),"{サービス}",設定!$B$5),"{料金}",設定!$B$7),"{日付1}",設定!$B$8),"{日付2}",設定!$B$9),"{時間1}",設定!$B$10),"{時間2}",設定!$B$11),"{時間}","（指定時間）"),"{日付確定}","（確定日）"),"{時間確定}","（確定時間）")) | U7: =IFERROR(VLOOKUP(CZ7,スクリプト_フロー!$A:$F,4,FALSE),"") | V7: =IF(U7="","",U7) | X7: =IF(DC7="","",SUBSTITUTE(SUBSTITUTE(SUBSTITUTE(SUBSTITUTE(SUBSTITUTE(SUBSTITUTE(SUBSTITUTE(SUBSTITUTE(SUBSTITUTE(SUBSTITUTE(SUBSTITUTE(DC7,"{会社}",設定!$B$3),"{自分}",設定!$B$4),"{サービス}",設定!$B$5),"{料金}",設定!$B$7),"{日付1}",設定!$B$8),"{日付2}",設定!$B$9),"{時間1}",設定!$B$10),"{時間2}",設定!$B$11),"{時間}","（指定時間）"),"{日付確定}","（確定日）"),"{時間確定}","（確定時間）")) | Y7: =IFERROR(VLOOKUP(DB7,スクリプト_フロー!$A:$F,4,FALSE),"") | Z7: =IF(Y7="","",Y7) | AA7: ⑤資料送付打診 | AB7: =IF(DE7="","",SUBSTITUTE(SUBSTITUTE(SUBSTITUTE(SUBSTITUTE(SUBSTITUTE(SUBSTITUTE(SUBSTITUTE(SUBSTITUTE(SUBSTITUTE(SUBSTITUTE(SUBSTITUTE(DE7,"{会社}",設定!$B$3),"{自分}",設定!$B$4),"{サービス}",設定!$B$5),"{料金}",設定!$B$7),"{日付1}",設定!$B$8),"{日付2}",設定!$B$9),"{時間1}",設定!$B$10),"{時間2}",設定!$B$11),"{時間}","（指定時間）"),"{日付確定}","（確定日）"),"{時間確定}","（確定時間）")) | AC7: =IFERROR(VLOOKUP(DD7,スクリプト_フロー!$A:$F,4,FALSE),"") | AD7: =IF(AC7="","",AC7) | AE7: RESPX_006 | AF7: =IF(DG7="","",SUBSTITUTE(SUBSTITUTE(SUBSTITUTE(SUBSTITUTE(SUBSTITUTE(SUBSTITUTE(SUBSTITUTE(SUBSTITUTE(SUBSTITUTE(SUBSTITUTE(SUBSTITUTE(DG7,"{会社}",設定!$B$3),"{自分}",設定!$B$4),"{サービス}",設定!$B$5),"{料金}",設定!$B$7),"{日付1}",設定!$B$8),"{日付2}",設定!$B$9),"{時間1}",設定!$B$10),"{時間2}",設定!$B$11),"{時間}","（指定時間）"),"{日付確定}","（確定日）"),"{時間確定}","（確定時間）")) | AG7: =IFERROR(VLOOKUP(DF7,スクリプト_フロー!$A:$F,4,FALSE),"") | CZ7: =R7&"|"&S7 -> | | DA7: =IFERROR(VLOOKUP(CZ7,スクリプト_フロー!$A:$F,5,FALSE),"") | DB7: =V7&"|"&W7 -> | | DC7: =IFERROR(VLOOKUP(DB7,スクリプト_フロー!$A:$F,5,FALSE),"") | DD7: =Z7&"|"&AA7 -> |⑤資料送付打診 | DE7: =IFERROR(VLOOKUP(DD7,スクリプト_フロー!$A:$F,5,FALSE),"") | DF7: =AD7&"|"&AE7 -> |RESPX_006 | DG7: =IFERROR(VLOOKUP(DF7,スクリプト_フロー!$A:$F,5,FALSE),"")
A8: 7 | B8: おにやまホテル | C8: 0977-66-1121 | D8: 鉄輪 | G8: ①架電 | I8: =SUBSTITUTE(SUBSTITUTE(SUBSTITUTE(SUBSTITUTE(SUBSTITUTE(SUBSTITUTE(SUBSTITUTE(SUBSTITUTE(SUBSTITUTE(SUBSTITUTE(SUBSTITUTE(Q8,"{会社}",設定!$B$3),"{自分}",設定!$B$4),"{サービス}",設定!$B$5),"{料金}",設定!$B$7),"{日付1}",設定!$B$8),"{日付2}",設定!$B$9),"{時間1}",設定!$B$10),"{時間2}",設定!$B$11),"{時間}","（指定時間）"),"{日付確定}","（確定日）"),"{時間確定}","（確定時間）") | J8: =IFERROR(VLOOKUP(P8,スクリプト_フロー!$A:$F,4,FALSE),"") | K8: 未架電 | P8: =G8&"|"&H8 -> ①架電| | Q8: =IFERROR(VLOOKUP(P8,スクリプト_フロー!$A:$F,5,FALSE),"") | R8: =IF(J8="","",J8) | T8: =IF(DA8="","",SUBSTITUTE(SUBSTITUTE(SUBSTITUTE(SUBSTITUTE(SUBSTITUTE(SUBSTITUTE(SUBSTITUTE(SUBSTITUTE(SUBSTITUTE(SUBSTITUTE(SUBSTITUTE(DA8,"{会社}",設定!$B$3),"{自分}",設定!$B$4),"{サービス}",設定!$B$5),"{料金}",設定!$B$7),"{日付1}",設定!$B$8),"{日付2}",設定!$B$9),"{時間1}",設定!$B$10),"{時間2}",設定!$B$11),"{時間}","（指定時間）"),"{日付確定}","（確定日）"),"{時間確定}","（確定時間）")) | U8: =IFERROR(VLOOKUP(CZ8,スクリプト_フロー!$A:$F,4,FALSE),"") | V8: =IF(U8="","",U8) | X8: =IF(DC8="","",SUBSTITUTE(SUBSTITUTE(SUBSTITUTE(SUBSTITUTE(SUBSTITUTE(SUBSTITUTE(SUBSTITUTE(SUBSTITUTE(SUBSTITUTE(SUBSTITUTE(SUBSTITUTE(DC8,"{会社}",設定!$B$3),"{自分}",設定!$B$4),"{サービス}",設定!$B$5),"{料金}",設定!$B$7),"{日付1}",設定!$B$8),"{日付2}",設定!$B$9),"{時間1}",設定!$B$10),"{時間2}",設定!$B$11),"{時間}","（指定時間）"),"{日付確定}","（確定日）"),"{時間確定}","（確定時間）")) | Y8: =IFERROR(VLOOKUP(DB8,スクリプト_フロー!$A:$F,4,FALSE),"") | Z8: =IF(Y8="","",Y8) | AA8: ⑥目的伝達 | AB8: =IF(DE8="","",SUBSTITUTE(SUBSTITUTE(SUBSTITUTE(SUBSTITUTE(SUBSTITUTE(SUBSTITUTE(SUBSTITUTE(SUBSTITUTE(SUBSTITUTE(SUBSTITUTE(SUBSTITUTE(DE8,"{会社}",設定!$B$3),"{自分}",設定!$B$4),"{サービス}",設定!$B$5),"{料金}",設定!$B$7),"{日付1}",設定!$B$8),"{日付2}",設定!$B$9),"{時間1}",設定!$B$10),"{時間2}",設定!$B$11),"{時間}","（指定時間）"),"{日付確定}","（確定日）"),"{時間確定}","（確定時間）")) | AC8: =IFERROR(VLOOKUP(DD8,スクリプト_フロー!$A:$F,4,FALSE),"") | AD8: =IF(AC8="","",AC8) | AE8: RESPX_007 | AF8: =IF(DG8="","",SUBSTITUTE(SUBSTITUTE(SUBSTITUTE(SUBSTITUTE(SUBSTITUTE(SUBSTITUTE(SUBSTITUTE(SUBSTITUTE(SUBSTITUTE(SUBSTITUTE(SUBSTITUTE(DG8,"{会社}",設定!$B$3),"{自分}",設定!$B$4),"{サービス}",設定!$B$5),"{料金}",設定!$B$7),"{日付1}",設定!$B$8),"{日付2}",設定!$B$9),"{時間1}",設定!$B$10),"{時間2}",設定!$B$11),"{時間}","（指定時間）"),"{日付確定}","（確定日）"),"{時間確定}","（確定時間）")) | AG8: =IFERROR(VLOOKUP(DF8,スクリプト_フロー!$A:$F,4,FALSE),"") | CZ8: =R8&"|"&S8 -> | | DA8: =IFERROR(VLOOKUP(CZ8,スクリプト_フロー!$A:$F,5,FALSE),"") | DB8: =V8&"|"&W8 -> | | DC8: =IFERROR(VLOOKUP(DB8,スクリプト_フロー!$A:$F,5,FALSE),"") | DD8: =Z8&"|"&AA8 -> |⑥目的伝達 | DE8: =IFERROR(VLOOKUP(DD8,スクリプト_フロー!$A:$F,5,FALSE),"") | DF8: =AD8&"|"&AE8 -> |RESPX_007 | DG8: =IFERROR(VLOOKUP(DF8,スクリプト_フロー!$A:$F,5,FALSE),"")
A9: 8 | B9: 別府八湯 御宿 野乃別府 | C9: 0977-21-5489 | D9: 別府駅周辺 | G9: ①架電 | I9: =SUBSTITUTE(SUBSTITUTE(SUBSTITUTE(SUBSTITUTE(SUBSTITUTE(SUBSTITUTE(SUBSTITUTE(SUBSTITUTE(SUBSTITUTE(SUBSTITUTE(SUBSTITUTE(Q9,"{会社}",設定!$B$3),"{自分}",設定!$B$4),"{サービス}",設定!$B$5),"{料金}",設定!$B$7),"{日付1}",設定!$B$8),"{日付2}",設定!$B$9),"{時間1}",設定!$B$10),"{時間2}",設定!$B$11),"{時間}","（指定時間）"),"{日付確定}","（確定日）"),"{時間確定}","（確定時間）") | J9: =IFERROR(VLOOKUP(P9,スクリプト_フロー!$A:$F,4,FALSE),"") | K9: 未架電 | P9: =G9&"|"&H9 -> ①架電| | Q9: =IFERROR(VLOOKUP(P9,スクリプト_フロー!$A:$F,5,FALSE),"") | R9: =IF(J9="","",J9) | T9: =IF(DA9="","",SUBSTITUTE(SUBSTITUTE(SUBSTITUTE(SUBSTITUTE(SUBSTITUTE(SUBSTITUTE(SUBSTITUTE(SUBSTITUTE(SUBSTITUTE(SUBSTITUTE(SUBSTITUTE(DA9,"{会社}",設定!$B$3),"{自分}",設定!$B$4),"{サービス}",設定!$B$5),"{料金}",設定!$B$7),"{日付1}",設定!$B$8),"{日付2}",設定!$B$9),"{時間1}",設定!$B$10),"{時間2}",設定!$B$11),"{時間}","（指定時間）"),"{日付確定}","（確定日）"),"{時間確定}","（確定時間）")) | U9: =IFERROR(VLOOKUP(CZ9,スクリプト_フロー!$A:$F,4,FALSE),"") | V9: =IF(U9="","",U9) | X9: =IF(DC9="","",SUBSTITUTE(SUBSTITUTE(SUBSTITUTE(SUBSTITUTE(SUBSTITUTE(SUBSTITUTE(SUBSTITUTE(SUBSTITUTE(SUBSTITUTE(SUBSTITUTE(SUBSTITUTE(DC9,"{会社}",設定!$B$3),"{自分}",設定!$B$4),"{サービス}",設定!$B$5),"{料金}",設定!$B$7),"{日付1}",設定!$B$8),"{日付2}",設定!$B$9),"{時間1}",設定!$B$10),"{時間2}",設定!$B$11),"{時間}","（指定時間）"),"{日付確定}","（確定日）"),"{時間確定}","（確定時間）")) | Y9: =IFERROR(VLOOKUP(DB9,スクリプト_フロー!$A:$F,4,FALSE),"") | Z9: =IF(Y9="","",Y9) | AA9: ⑦メリット | AB9: =IF(DE9="","",SUBSTITUTE(SUBSTITUTE(SUBSTITUTE(SUBSTITUTE(SUBSTITUTE(SUBSTITUTE(SUBSTITUTE(SUBSTITUTE(SUBSTITUTE(SUBSTITUTE(SUBSTITUTE(DE9,"{会社}",設定!$B$3),"{自分}",設定!$B$4),"{サービス}",設定!$B$5),"{料金}",設定!$B$7),"{日付1}",設定!$B$8),"{日付2}",設定!$B$9),"{時間1}",設定!$B$10),"{時間2}",設定!$B$11),"{時間}","（指定時間）"),"{日付確定}","（確定日）"),"{時間確定}","（確定時間）")) | AC9: =IFERROR(VLOOKUP(DD9,スクリプト_フロー!$A:$F,4,FALSE),"") | AD9: =IF(AC9="","",AC9) | AE9: RESPX_008 | AF9: =IF(DG9="","",SUBSTITUTE(SUBSTITUTE(SUBSTITUTE(SUBSTITUTE(SUBSTITUTE(SUBSTITUTE(SUBSTITUTE(SUBSTITUTE(SUBSTITUTE(SUBSTITUTE(SUBSTITUTE(DG9,"{会社}",設定!$B$3),"{自分}",設定!$B$4),"{サービス}",設定!$B$5),"{料金}",設定!$B$7),"{日付1}",設定!$B$8),"{日付2}",設定!$B$9),"{時間1}",設定!$B$10),"{時間2}",設定!$B$11),"{時間}","（指定時間）"),"{日付確定}","（確定日）"),"{時間確定}","（確定時間）")) | AG9: =IFERROR(VLOOKUP(DF9,スクリプト_フロー!$A:$F,4,FALSE),"") | CZ9: =R9&"|"&S9 -> | | DA9: =IFERROR(VLOOKUP(CZ9,スクリプト_フロー!$A:$F,5,FALSE),"") | DB9: =V9&"|"&W9 -> | | DC9: =IFERROR(VLOOKUP(DB9,スクリプト_フロー!$A:$F,5,FALSE),"") | DD9: =Z9&"|"&AA9 -> |⑦メリット | DE9: =IFERROR(VLOOKUP(DD9,スクリプト_フロー!$A:$F,5,FALSE),"") | DF9: =AD9&"|"&AE9 -> |RESPX_008 | DG9: =IFERROR(VLOOKUP(DF9,スクリプト_フロー!$A:$F,5,FALSE),"")
A10: 9 | B10: アマネク別府ゆらり | C10: 0977-76-5566 | D10: 別府駅周辺 | G10: ①架電 | I10: =SUBSTITUTE(SUBSTITUTE(SUBSTITUTE(SUBSTITUTE(SUBSTITUTE(SUBSTITUTE(SUBSTITUTE(SUBSTITUTE(SUBSTITUTE(SUBSTITUTE(SUBSTITUTE(Q10,"{会社}",設定!$B$3),"{自分}",設定!$B$4),"{サービス}",設定!$B$5),"{料金}",設定!$B$7),"{日付1}",設定!$B$8),"{日付2}",設定!$B$9),"{時間1}",設定!$B$10),"{時間2}",設定!$B$11),"{時間}","（指定時間）"),"{日付確定}","（確定日）"),"{時間確定}","（確定時間）") | J10: =IFERROR(VLOOKUP(P10,スクリプト_フロー!$A:$F,4,FALSE),"") | K10: 未架電 | P10: =G10&"|"&H10 -> ①架電| | Q10: =IFERROR(VLOOKUP(P10,スクリプト_フロー!$A:$F,5,FALSE),"") | R10: =IF(J10="","",J10) | T10: =IF(DA10="","",SUBSTITUTE(SUBSTITUTE(SUBSTITUTE(SUBSTITUTE(SUBSTITUTE(SUBSTITUTE(SUBSTITUTE(SUBSTITUTE(SUBSTITUTE(SUBSTITUTE(SUBSTITUTE(DA10,"{会社}",設定!$B$3),"{自分}",設定!$B$4),"{サービス}",設定!$B$5),"{料金}",設定!$B$7),"{日付1}",設定!$B$8),"{日付2}",設定!$B$9),"{時間1}",設定!$B$10),"{時間2}",設定!$B$11),"{時間}","（指定時間）"),"{日付確定}","（確定日）"),"{時間確定}","（確定時間）")) | U10: =IFERROR(VLOOKUP(CZ10,スクリプト_フロー!$A:$F,4,FALSE),"") | V10: =IF(U10="","",U10) | X10: =IF(DC10="","",SUBSTITUTE(SUBSTITUTE(SUBSTITUTE(SUBSTITUTE(SUBSTITUTE(SUBSTITUTE(SUBSTITUTE(SUBSTITUTE(SUBSTITUTE(SUBSTITUTE(SUBSTITUTE(DC10,"{会社}",設定!$B$3),"{自分}",設定!$B$4),"{サービス}",設定!$B$5),"{料金}",設定!$B$7),"{日付1}",設定!$B$8),"{日付2}",設定!$B$9),"{時間1}",設定!$B$10),"{時間2}",設定!$B$11),"{時間}","（指定時間）"),"{日付確定}","（確定日）"),"{時間確定}","（確定時間）")) | Y10: =IFERROR(VLOOKUP(DB10,スクリプト_フロー!$A:$F,4,FALSE),"") | Z10: =IF(Y10="","",Y10) | AA10: ⑧費用説明 | AB10: =IF(DE10="","",SUBSTITUTE(SUBSTITUTE(SUBSTITUTE(SUBSTITUTE(SUBSTITUTE(SUBSTITUTE(SUBSTITUTE(SUBSTITUTE(SUBSTITUTE(SUBSTITUTE(SUBSTITUTE(DE10,"{会社}",設定!$B$3),"{自分}",設定!$B$4),"{サービス}",設定!$B$5),"{料金}",設定!$B$7),"{日付1}",設定!$B$8),"{日付2}",設定!$B$9),"{時間1}",設定!$B$10),"{時間2}",設定!$B$11),"{時間}","（指定時間）"),"{日付確定}","（確定日）"),"{時間確定}","（確定時間）")) | AC10: =IFERROR(VLOOKUP(DD10,スクリプト_フロー!$A:$F,4,FALSE),"") | AD10: =IF(AC10="","",AC10) | AE10: RESPX_009 | AF10: =IF(DG10="","",SUBSTITUTE(SUBSTITUTE(SUBSTITUTE(SUBSTITUTE(SUBSTITUTE(SUBSTITUTE(SUBSTITUTE(SUBSTITUTE(SUBSTITUTE(SUBSTITUTE(SUBSTITUTE(DG10,"{会社}",設定!$B$3),"{自分}",設定!$B$4),"{サービス}",設定!$B$5),"{料金}",設定!$B$7),"{日付1}",設定!$B$8),"{日付2}",設定!$B$9),"{時間1}",設定!$B$10),"{時間2}",設定!$B$11),"{時間}","（指定時間）"),"{日付確定}","（確定日）"),"{時間確定}","（確定時間）")) | AG10: =IFERROR(VLOOKUP(DF10,スクリプト_フロー!$A:$F,4,FALSE),"") | CZ10: =R10&"|"&S10 -> | | DA10: =IFERROR(VLOOKUP(CZ10,スクリプト_フロー!$A:$F,5,FALSE),"") | DB10: =V10&"|"&W10 -> | | DC10: =IFERROR(VLOOKUP(DB10,スクリプト_フロー!$A:$F,5,FALSE),"") | DD10: =Z10&"|"&AA10 -> |⑧費用説明 | DE10: =IFERROR(VLOOKUP(DD10,スクリプト_フロー!$A:$F,5,FALSE),"") | DF10: =AD10&"|"&AE10 -> |RESPX_009 | DG10: =IFERROR(VLOOKUP(DF10,スクリプト_フロー!$A:$F,5,FALSE),"")
A11: 10 | B11: アマネクイン別府 | C11: 0977-76-5565 | D11: 別府駅周辺 | G11: ①架電 | I11: =SUBSTITUTE(SUBSTITUTE(SUBSTITUTE(SUBSTITUTE(SUBSTITUTE(SUBSTITUTE(SUBSTITUTE(SUBSTITUTE(SUBSTITUTE(SUBSTITUTE(SUBSTITUTE(Q11,"{会社}",設定!$B$3),"{自分}",設定!$B$4),"{サービス}",設定!$B$5),"{料金}",設定!$B$7),"{日付1}",設定!$B$8),"{日付2}",設定!$B$9),"{時間1}",設定!$B$10),"{時間2}",設定!$B$11),"{時間}","（指定時間）"),"{日付確定}","（確定日）"),"{時間確定}","（確定時間）") | J11: =IFERROR(VLOOKUP(P11,スクリプト_フロー!$A:$F,4,FALSE),"") | K11: 未架電 | P11: =G11&"|"&H11 -> ①架電| | Q11: =IFERROR(VLOOKUP(P11,スクリプト_フロー!$A:$F,5,FALSE),"") | R11: =IF(J11="","",J11) | T11: =IF(DA11="","",SUBSTITUTE(SUBSTITUTE(SUBSTITUTE(SUBSTITUTE(SUBSTITUTE(SUBSTITUTE(SUBSTITUTE(SUBSTITUTE(SUBSTITUTE(SUBSTITUTE(SUBSTITUTE(DA11,"{会社}",設定!$B$3),"{自分}",設定!$B$4),"{サービス}",設定!$B$5),"{料金}",設定!$B$7),"{日付1}",設定!$B$8),"{日付2}",設定!$B$9),"{時間1}",設定!$B$10),"{時間2}",設定!$B$11),"{時間}","（指定時間）"),"{日付確定}","（確定日）"),"{時間確定}","（確定時間）")) | U11: =IFERROR(VLOOKUP(CZ11,スクリプト_フロー!$A:$F,4,FALSE),"") | V11: =IF(U11="","",U11) | X11: =IF(DC11="","",SUBSTITUTE(SUBSTITUTE(SUBSTITUTE(SUBSTITUTE(SUBSTITUTE(SUBSTITUTE(SUBSTITUTE(SUBSTITUTE(SUBSTITUTE(SUBSTITUTE(SUBSTITUTE(DC11,"{会社}",設定!$B$3),"{自分}",設定!$B$4),"{サービス}",設定!$B$5),"{料金}",設定!$B$7),"{日付1}",設定!$B$8),"{日付2}",設定!$B$9),"{時間1}",設定!$B$10),"{時間2}",設定!$B$11),"{時間}","（指定時間）"),"{日付確定}","（確定日）"),"{時間確定}","（確定時間）")) | Y11: =IFERROR(VLOOKUP(DB11,スクリプト_フロー!$A:$F,4,FALSE),"") | Z11: =IF(Y11="","",Y11) | AA11: ⑨安全説明 | AB11: =IF(DE11="","",SUBSTITUTE(SUBSTITUTE(SUBSTITUTE(SUBSTITUTE(SUBSTITUTE(SUBSTITUTE(SUBSTITUTE(SUBSTITUTE(SUBSTITUTE(SUBSTITUTE(SUBSTITUTE(DE11,"{会社}",設定!$B$3),"{自分}",設定!$B$4),"{サービス}",設定!$B$5),"{料金}",設定!$B$7),"{日付1}",設定!$B$8),"{日付2}",設定!$B$9),"{時間1}",設定!$B$10),"{時間2}",設定!$B$11),"{時間}","（指定時間）"),"{日付確定}","（確定日）"),"{時間確定}","（確定時間）")) | AC11: =IFERROR(VLOOKUP(DD11,スクリプト_フロー!$A:$F,4,FALSE),"") | AD11: =IF(AC11="","",AC11) | AE11: RESPX_010 | AF11: =IF(DG11="","",SUBSTITUTE(SUBSTITUTE(SUBSTITUTE(SUBSTITUTE(SUBSTITUTE(SUBSTITUTE(SUBSTITUTE(SUBSTITUTE(SUBSTITUTE(SUBSTITUTE(SUBSTITUTE(DG11,"{会社}",設定!$B$3),"{自分}",設定!$B$4),"{サービス}",設定!$B$5),"{料金}",設定!$B$7),"{日付1}",設定!$B$8),"{日付2}",設定!$B$9),"{時間1}",設定!$B$10),"{時間2}",設定!$B$11),"{時間}","（指定時間）"),"{日付確定}","（確定日）"),"{時間確定}","（確定時間）")) | AG11: =IFERROR(VLOOKUP(DF11,スクリプト_フロー!$A:$F,4,FALSE),"") | CZ11: =R11&"|"&S11 -> | | DA11: =IFERROR(VLOOKUP(CZ11,スクリプト_フロー!$A:$F,5,FALSE),"") | DB11: =V11&"|"&W11 -> | | DC11: =IFERROR(VLOOKUP(DB11,スクリプト_フロー!$A:$F,5,FALSE),"") | DD11: =Z11&"|"&AA11 -> |⑨安全説明 | DE11: =IFERROR(VLOOKUP(DD11,スクリプト_フロー!$A:$F,5,FALSE),"") | DF11: =AD11&"|"&AE11 -> |RESPX_010 | DG11: =IFERROR(VLOOKUP(DF11,スクリプト_フロー!$A:$F,5,FALSE),"")
A12: 11 | B12: MURE Beppu | C12: 0977-23-3377 | D12: 楠町（ゆめタウン周辺） | G12: ①架電 | I12: =SUBSTITUTE(SUBSTITUTE(SUBSTITUTE(SUBSTITUTE(SUBSTITUTE(SUBSTITUTE(SUBSTITUTE(SUBSTITUTE(SUBSTITUTE(SUBSTITUTE(SUBSTITUTE(Q12,"{会社}",設定!$B$3),"{自分}",設定!$B$4),"{サービス}",設定!$B$5),"{料金}",設定!$B$7),"{日付1}",設定!$B$8),"{日付2}",設定!$B$9),"{時間1}",設定!$B$10),"{時間2}",設定!$B$11),"{時間}","（指定時間）"),"{日付確定}","（確定日）"),"{時間確定}","（確定時間）") | J12: =IFERROR(VLOOKUP(P12,スクリプト_フロー!$A:$F,4,FALSE),"") | K12: 未架電 | P12: =G12&"|"&H12 -> ①架電| | Q12: =IFERROR(VLOOKUP(P12,スクリプト_フロー!$A:$F,5,FALSE),"") | R12: =IF(J12="","",J12) | T12: =IF(DA12="","",SUBSTITUTE(SUBSTITUTE(SUBSTITUTE(SUBSTITUTE(SUBSTITUTE(SUBSTITUTE(SUBSTITUTE(SUBSTITUTE(SUBSTITUTE(SUBSTITUTE(SUBSTITUTE(DA12,"{会社}",設定!$B$3),"{自分}",設定!$B$4),"{サービス}",設定!$B$5),"{料金}",設定!$B$7),"{日付1}",設定!$B$8),"{日付2}",設定!$B$9),"{時間1}",設定!$B$10),"{時間2}",設定!$B$11),"{時間}","（指定時間）"),"{日付確定}","（確定日）"),"{時間確定}","（確定時間）")) | U12: =IFERROR(VLOOKUP(CZ12,スクリプト_フロー!$A:$F,4,FALSE),"") | V12: =IF(U12="","",U12) | X12: =IF(DC12="","",SUBSTITUTE(SUBSTITUTE(SUBSTITUTE(SUBSTITUTE(SUBSTITUTE(SUBSTITUTE(SUBSTITUTE(SUBSTITUTE(SUBSTITUTE(SUBSTITUTE(SUBSTITUTE(DC12,"{会社}",設定!$B$3),"{自分}",設定!$B$4),"{サービス}",設定!$B$5),"{料金}",設定!$B$7),"{日付1}",設定!$B$8),"{日付2}",設定!$B$9),"{時間1}",設定!$B$10),"{時間2}",設定!$B$11),"{時間}","（指定時間）"),"{日付確定}","（確定日）"),"{時間確定}","（確定時間）")) | Y12: =IFERROR(VLOOKUP(DB12,スクリプト_フロー!$A:$F,4,FALSE),"") | Z12: =IF(Y12="","",Y12) | AA12: ⑩ヒアリング | AB12: =IF(DE12="","",SUBSTITUTE(SUBSTITUTE(SUBSTITUTE(SUBSTITUTE(SUBSTITUTE(SUBSTITUTE(SUBSTITUTE(SUBSTITUTE(SUBSTITUTE(SUBSTITUTE(SUBSTITUTE(DE12,"{会社}",設定!$B$3),"{自分}",設定!$B$4),"{サービス}",設定!$B$5),"{料金}",設定!$B$7),"{日付1}",設定!$B$8),"{日付2}",設定!$B$9),"{時間1}",設定!$B$10),"{時間2}",設定!$B$11),"{時間}","（指定時間）"),"{日付確定}","（確定日）"),"{時間確定}","（確定時間）")) | AC12: =IFERROR(VLOOKUP(DD12,スクリプト_フロー!$A:$F,4,FALSE),"") | AD12: =IF(AC12="","",AC12) | AE12: RESPX_011 | AF12: =IF(DG12="","",SUBSTITUTE(SUBSTITUTE(SUBSTITUTE(SUBSTITUTE(SUBSTITUTE(SUBSTITUTE(SUBSTITUTE(SUBSTITUTE(SUBSTITUTE(SUBSTITUTE(SUBSTITUTE(DG12,"{会社}",設定!$B$3),"{自分}",設定!$B$4),"{サービス}",設定!$B$5),"{料金}",設定!$B$7),"{日付1}",設定!$B$8),"{日付2}",設定!$B$9),"{時間1}",設定!$B$10),"{時間2}",設定!$B$11),"{時間}","（指定時間）"),"{日付確定}","（確定日）"),"{時間確定}","（確定時間）")) | AG12: =IFERROR(VLOOKUP(DF12,スクリプト_フロー!$A:$F,4,FALSE),"") | CZ12: =R12&"|"&S12 -> | | DA12: =IFERROR(VLOOKUP(CZ12,スクリプト_フロー!$A:$F,5,FALSE),"") | DB12: =V12&"|"&W12 -> | | DC12: =IFERROR(VLOOKUP(DB12,スクリプト_フロー!$A:$F,5,FALSE),"") | DD12: =Z12&"|"&AA12 -> |⑩ヒアリング | DE12: =IFERROR(VLOOKUP(DD12,スクリプト_フロー!$A:$F,5,FALSE),"") | DF12: =AD12&"|"&AE12 -> |RESPX_011 | DG12: =IFERROR(VLOOKUP(DF12,スクリプト_フロー!$A:$F,5,FALSE),"")
A13: 12 | B13: REX HOTEL別府 | C13: 0977-23-6111 | D13: 若草・餅ヶ浜 | G13: ①架電 | I13: =SUBSTITUTE(SUBSTITUTE(SUBSTITUTE(SUBSTITUTE(SUBSTITUTE(SUBSTITUTE(SUBSTITUTE(SUBSTITUTE(SUBSTITUTE(SUBSTITUTE(SUBSTITUTE(Q13,"{会社}",設定!$B$3),"{自分}",設定!$B$4),"{サービス}",設定!$B$5),"{料金}",設定!$B$7),"{日付1}",設定!$B$8),"{日付2}",設定!$B$9),"{時間1}",設定!$B$10),"{時間2}",設定!$B$11),"{時間}","（指定時間）"),"{日付確定}","（確定日）"),"{時間確定}","（確定時間）") | J13: =IFERROR(VLOOKUP(P13,スクリプト_フロー!$A:$F,4,FALSE),"") | K13: 未架電 | P13: =G13&"|"&H13 -> ①架電| | Q13: =IFERROR(VLOOKUP(P13,スクリプト_フロー!$A:$F,5,FALSE),"") | R13: =IF(J13="","",J13) | T13: =IF(DA13="","",SUBSTITUTE(SUBSTITUTE(SUBSTITUTE(SUBSTITUTE(SUBSTITUTE(SUBSTITUTE(SUBSTITUTE(SUBSTITUTE(SUBSTITUTE(SUBSTITUTE(SUBSTITUTE(DA13,"{会社}",設定!$B$3),"{自分}",設定!$B$4),"{サービス}",設定!$B$5),"{料金}",設定!$B$7),"{日付1}",設定!$B$8),"{日付2}",設定!$B$9),"{時間1}",設定!$B$10),"{時間2}",設定!$B$11),"{時間}","（指定時間）"),"{日付確定}","（確定日）"),"{時間確定}","（確定時間）")) | U13: =IFERROR(VLOOKUP(CZ13,スクリプト_フロー!$A:$F,4,FALSE),"") | V13: =IF(U13="","",U13) | X13: =IF(DC13="","",SUBSTITUTE(SUBSTITUTE(SUBSTITUTE(SUBSTITUTE(SUBSTITUTE(SUBSTITUTE(SUBSTITUTE(SUBSTITUTE(SUBSTITUTE(SUBSTITUTE(SUBSTITUTE(DC13,"{会社}",設定!$B$3),"{自分}",設定!$B$4),"{サービス}",設定!$B$5),"{料金}",設定!$B$7),"{日付1}",設定!$B$8),"{日付2}",設定!$B$9),"{時間1}",設定!$B$10),"{時間2}",設定!$B$11),"{時間}","（指定時間）"),"{日付確定}","（確定日）"),"{時間確定}","（確定時間）")) | Y13: =IFERROR(VLOOKUP(DB13,スクリプト_フロー!$A:$F,4,FALSE),"") | Z13: =IF(Y13="","",Y13) | AA13: ⑪代替案 | AB13: =IF(DE13="","",SUBSTITUTE(SUBSTITUTE(SUBSTITUTE(SUBSTITUTE(SUBSTITUTE(SUBSTITUTE(SUBSTITUTE(SUBSTITUTE(SUBSTITUTE(SUBSTITUTE(SUBSTITUTE(DE13,"{会社}",設定!$B$3),"{自分}",設定!$B$4),"{サービス}",設定!$B$5),"{料金}",設定!$B$7),"{日付1}",設定!$B$8),"{日付2}",設定!$B$9),"{時間1}",設定!$B$10),"{時間2}",設定!$B$11),"{時間}","（指定時間）"),"{日付確定}","（確定日）"),"{時間確定}","（確定時間）")) | AC13: =IFERROR(VLOOKUP(DD13,スクリプト_フロー!$A:$F,4,FALSE),"") | AD13: =IF(AC13="","",AC13) | AE13: RESPX_012 | AF13: =IF(DG13="","",SUBSTITUTE(SUBSTITUTE(SUBSTITUTE(SUBSTITUTE(SUBSTITUTE(SUBSTITUTE(SUBSTITUTE(SUBSTITUTE(SUBSTITUTE(SUBSTITUTE(SUBSTITUTE(DG13,"{会社}",設定!$B$3),"{自分}",設定!$B$4),"{サービス}",設定!$B$5),"{料金}",設定!$B$7),"{日付1}",設定!$B$8),"{日付2}",設定!$B$9),"{時間1}",設定!$B$10),"{時間2}",設定!$B$11),"{時間}","（指定時間）"),"{日付確定}","（確定日）"),"{時間確定}","（確定時間）")) | AG13: =IFERROR(VLOOKUP(DF13,スクリプト_フロー!$A:$F,4,FALSE),"") | CZ13: =R13&"|"&S13 -> | | DA13: =IFERROR(VLOOKUP(CZ13,スクリプト_フロー!$A:$F,5,FALSE),"") | DB13: =V13&"|"&W13 -> | | DC13: =IFERROR(VLOOKUP(DB13,スクリプト_フロー!$A:$F,5,FALSE),"") | DD13: =Z13&"|"&AA13 -> |⑪代替案 | DE13: =IFERROR(VLOOKUP(DD13,スクリプト_フロー!$A:$F,5,FALSE),"") | DF13: =AD13&"|"&AE13 -> |RESPX_012 | DG13: =IFERROR(VLOOKUP(DF13,スクリプト_フロー!$A:$F,5,FALSE),"")
A14: 13 | B14: 別府風雅 | C14: 0570-018-766 | D14: 堀田 | G14: ①架電 | I14: =SUBSTITUTE(SUBSTITUTE(SUBSTITUTE(SUBSTITUTE(SUBSTITUTE(SUBSTITUTE(SUBSTITUTE(SUBSTITUTE(SUBSTITUTE(SUBSTITUTE(SUBSTITUTE(Q14,"{会社}",設定!$B$3),"{自分}",設定!$B$4),"{サービス}",設定!$B$5),"{料金}",設定!$B$7),"{日付1}",設定!$B$8),"{日付2}",設定!$B$9),"{時間1}",設定!$B$10),"{時間2}",設定!$B$11),"{時間}","（指定時間）"),"{日付確定}","（確定日）"),"{時間確定}","（確定時間）") | J14: =IFERROR(VLOOKUP(P14,スクリプト_フロー!$A:$F,4,FALSE),"") | K14: 未架電 | P14: =G14&"|"&H14 -> ①架電| | Q14: =IFERROR(VLOOKUP(P14,スクリプト_フロー!$A:$F,5,FALSE),"") | R14: =IF(J14="","",J14) | T14: =IF(DA14="","",SUBSTITUTE(SUBSTITUTE(SUBSTITUTE(SUBSTITUTE(SUBSTITUTE(SUBSTITUTE(SUBSTITUTE(SUBSTITUTE(SUBSTITUTE(SUBSTITUTE(SUBSTITUTE(DA14,"{会社}",設定!$B$3),"{自分}",設定!$B$4),"{サービス}",設定!$B$5),"{料金}",設定!$B$7),"{日付1}",設定!$B$8),"{日付2}",設定!$B$9),"{時間1}",設定!$B$10),"{時間2}",設定!$B$11),"{時間}","（指定時間）"),"{日付確定}","（確定日）"),"{時間確定}","（確定時間）")) | U14: =IFERROR(VLOOKUP(CZ14,スクリプト_フロー!$A:$F,4,FALSE),"") | V14: =IF(U14="","",U14) | X14: =IF(DC14="","",SUBSTITUTE(SUBSTITUTE(SUBSTITUTE(SUBSTITUTE(SUBSTITUTE(SUBSTITUTE(SUBSTITUTE(SUBSTITUTE(SUBSTITUTE(SUBSTITUTE(SUBSTITUTE(DC14,"{会社}",設定!$B$3),"{自分}",設定!$B$4),"{サービス}",設定!$B$5),"{料金}",設定!$B$7),"{日付1}",設定!$B$8),"{日付2}",設定!$B$9),"{時間1}",設定!$B$10),"{時間2}",設定!$B$11),"{時間}","（指定時間）"),"{日付確定}","（確定日）"),"{時間確定}","（確定時間）")) | Y14: =IFERROR(VLOOKUP(DB14,スクリプト_フロー!$A:$F,4,FALSE),"") | Z14: =IF(Y14="","",Y14) | AA14: ⑫決裁者確認 | AB14: =IF(DE14="","",SUBSTITUTE(SUBSTITUTE(SUBSTITUTE(SUBSTITUTE(SUBSTITUTE(SUBSTITUTE(SUBSTITUTE(SUBSTITUTE(SUBSTITUTE(SUBSTITUTE(SUBSTITUTE(DE14,"{会社}",設定!$B$3),"{自分}",設定!$B$4),"{サービス}",設定!$B$5),"{料金}",設定!$B$7),"{日付1}",設定!$B$8),"{日付2}",設定!$B$9),"{時間1}",設定!$B$10),"{時間2}",設定!$B$11),"{時間}","（指定時間）"),"{日付確定}","（確定日）"),"{時間確定}","（確定時間）")) | AC14: =IFERROR(VLOOKUP(DD14,スクリプト_フロー!$A:$F,4,FALSE),"") | AD14: =IF(AC14="","",AC14) | AE14: RESPX_013 | AF14: =IF(DG14="","",SUBSTITUTE(SUBSTITUTE(SUBSTITUTE(SUBSTITUTE(SUBSTITUTE(SUBSTITUTE(SUBSTITUTE(SUBSTITUTE(SUBSTITUTE(SUBSTITUTE(SUBSTITUTE(DG14,"{会社}",設定!$B$3),"{自分}",設定!$B$4),"{サービス}",設定!$B$5),"{料金}",設定!$B$7),"{日付1}",設定!$B$8),"{日付2}",設定!$B$9),"{時間1}",設定!$B$10),"{時間2}",設定!$B$11),"{時間}","（指定時間）"),"{日付確定}","（確定日）"),"{時間確定}","（確定時間）")) | AG14: =IFERROR(VLOOKUP(DF14,スクリプト_フロー!$A:$F,4,FALSE),"") | CZ14: =R14&"|"&S14 -> | | DA14: =IFERROR(VLOOKUP(CZ14,スクリプト_フロー!$A:$F,5,FALSE),"") | DB14: =V14&"|"&W14 -> | | DC14: =IFERROR(VLOOKUP(DB14,スクリプト_フロー!$A:$F,5,FALSE),"") | DD14: =Z14&"|"&AA14 -> |⑫決裁者確認 | DE14: =IFERROR(VLOOKUP(DD14,スクリプト_フロー!$A:$F,5,FALSE),"") | DF14: =AD14&"|"&AE14 -> |RESPX_013 | DG14: =IFERROR(VLOOKUP(DF14,スクリプト_フロー!$A:$F,5,FALSE),"")
... A20: 19 | B20: ホテルサンバリーアネックス | C20: 0977-26-6555 | D20: 石垣・浜脇周辺 | G20: ①架電 | I20: =SUBSTITUTE(SUBSTITUTE(SUBSTITUTE(SUBSTITUTE(SUBSTITUTE(SUBSTITUTE(SUBSTITUTE(SUBSTITUTE(SUBSTITUTE(SUBSTITUTE(SUBSTITUTE(Q20,"{会社}",設定!$B$3),"{自分}",設定!$B$4),"{サービス}",設定!$B$5),"{料金}",設定!$B$7),"{日付1}",設定!$B$8),"{日付2}",設定!$B$9),"{時間1}",設定!$B$10),"{時間2}",設定!$B$11),"{時間}","（指定時間）"),"{日付確定}","（確定日）"),"{時間確定}","（確定時間）") | J20: =IFERROR(VLOOKUP(P20,スクリプト_フロー!$A:$F,4,FALSE),"") | K20: 未架電 | P20: =G20&"|"&H20 -> ①架電| | Q20: =IFERROR(VLOOKUP(P20,スクリプト_フロー!$A:$F,5,FALSE),"") | R20: =IF(J20="","",J20) | T20: =IF(DA20="","",SUBSTITUTE(SUBSTITUTE(SUBSTITUTE(SUBSTITUTE(SUBSTITUTE(SUBSTITUTE(SUBSTITUTE(SUBSTITUTE(SUBSTITUTE(SUBSTITUTE(SUBSTITUTE(DA20,"{会社}",設定!$B$3),"{自分}",設定!$B$4),"{サービス}",設定!$B$5),"{料金}",設定!$B$7),"{日付1}",設定!$B$8),"{日付2}",設定!$B$9),"{時間1}",設定!$B$10),"{時間2}",設定!$B$11),"{時間}","（指定時間）"),"{日付確定}","（確定日）"),"{時間確定}","（確定時間）")) | U20: =IFERROR(VLOOKUP(CZ20,スクリプト_フロー!$A:$F,4,FALSE),"") | V20: =IF(U20="","",U20) | X20: =IF(DC20="","",SUBSTITUTE(SUBSTITUTE(SUBSTITUTE(SUBSTITUTE(SUBSTITUTE(SUBSTITUTE(SUBSTITUTE(SUBSTITUTE(SUBSTITUTE(SUBSTITUTE(SUBSTITUTE(DC20,"{会社}",設定!$B$3),"{自分}",設定!$B$4),"{サービス}",設定!$B$5),"{料金}",設定!$B$7),"{日付1}",設定!$B$8),"{日付2}",設定!$B$9),"{時間1}",設定!$B$10),"{時間2}",設定!$B$11),"{時間}","（指定時間）"),"{日付確定}","（確定日）"),"{時間確定}","（確定時間）")) | Y20: =IFERROR(VLOOKUP(DB20,スクリプト_フロー!$A:$F,4,FALSE),"") | Z20: =IF(Y20="","",Y20) | AA20: ⑱丁寧終了 | AB20: =IF(DE20="","",SUBSTITUTE(SUBSTITUTE(SUBSTITUTE(SUBSTITUTE(SUBSTITUTE(SUBSTITUTE(SUBSTITUTE(SUBSTITUTE(SUBSTITUTE(SUBSTITUTE(SUBSTITUTE(DE20,"{会社}",設定!$B$3),"{自分}",設定!$B$4),"{サービス}",設定!$B$5),"{料金}",設定!$B$7),"{日付1}",設定!$B$8),"{日付2}",設定!$B$9),"{時間1}",設定!$B$10),"{時間2}",設定!$B$11),"{時間}","（指定時間）"),"{日付確定}","（確定日）"),"{時間確定}","（確定時間）")) | AC20: =IFERROR(VLOOKUP(DD20,スクリプト_フロー!$A:$F,4,FALSE),"") | AD20: =IF(AC20="","",AC20) | AE20: RESPX_019 | AF20: =IF(DG20="","",SUBSTITUTE(SUBSTITUTE(SUBSTITUTE(SUBSTITUTE(SUBSTITUTE(SUBSTITUTE(SUBSTITUTE(SUBSTITUTE(SUBSTITUTE(SUBSTITUTE(SUBSTITUTE(DG20,"{会社}",設定!$B$3),"{自分}",設定!$B$4),"{サービス}",設定!$B$5),"{料金}",設定!$B$7),"{日付1}",設定!$B$8),"{日付2}",設定!$B$9),"{時間1}",設定!$B$10),"{時間2}",設定!$B$11),"{時間}","（指定時間）"),"{日付確定}","（確定日）"),"{時間確定}","（確定時間）")) | AG20: =IFERROR(VLOOKUP(DF20,スクリプト_フロー!$A:$F,4,FALSE),"") | CZ20: =R20&"|"&S20 -> | | DA20: =IFERROR(VLOOKUP(CZ20,スクリプト_フロー!$A:$F,5,FALSE),"") | DB20: =V20&"|"&W20 -> | | DC20: =IFERROR(VLOOKUP(DB20,スクリプト_フロー!$A:$F,5,FALSE),"") | DD20: =Z20&"|"&AA20 -> |⑱丁寧終了 | DE20: =IFERROR(VLOOKUP(DD20,スクリプト_フロー!$A:$F,5,FALSE),"") | DF20: =AD20&"|"&AE20 -> |RESPX_019 | DG20: =IFERROR(VLOOKUP(DF20,スクリプト_フロー!$A:$F,5,FALSE),"")
A21: 20 | B21: ビジネスホテル・グッドイン別府 | C21: 0977-22-3001 | D21: 浜町・浜脇 | G21: ①架電 | I21: =SUBSTITUTE(SUBSTITUTE(SUBSTITUTE(SUBSTITUTE(SUBSTITUTE(SUBSTITUTE(SUBSTITUTE(SUBSTITUTE(SUBSTITUTE(SUBSTITUTE(SUBSTITUTE(Q21,"{会社}",設定!$B$3),"{自分}",設定!$B$4),"{サービス}",設定!$B$5),"{料金}",設定!$B$7),"{日付1}",設定!$B$8),"{日付2}",設定!$B$9),"{時間1}",設定!$B$10),"{時間2}",設定!$B$11),"{時間}","（指定時間）"),"{日付確定}","（確定日）"),"{時間確定}","（確定時間）") | J21: =IFERROR(VLOOKUP(P21,スクリプト_フロー!$A:$F,4,FALSE),"") | K21: 未架電 | P21: =G21&"|"&H21 -> ①架電| | Q21: =IFERROR(VLOOKUP(P21,スクリプト_フロー!$A:$F,5,FALSE),"") | R21: =IF(J21="","",J21) | T21: =IF(DA21="","",SUBSTITUTE(SUBSTITUTE(SUBSTITUTE(SUBSTITUTE(SUBSTITUTE(SUBSTITUTE(SUBSTITUTE(SUBSTITUTE(SUBSTITUTE(SUBSTITUTE(SUBSTITUTE(DA21,"{会社}",設定!$B$3),"{自分}",設定!$B$4),"{サービス}",設定!$B$5),"{料金}",設定!$B$7),"{日付1}",設定!$B$8),"{日付2}",設定!$B$9),"{時間1}",設定!$B$10),"{時間2}",設定!$B$11),"{時間}","（指定時間）"),"{日付確定}","（確定日）"),"{時間確定}","（確定時間）")) | U21: =IFERROR(VLOOKUP(CZ21,スクリプト_フロー!$A:$F,4,FALSE),"") | V21: =IF(U21="","",U21) | X21: =IF(DC21="","",SUBSTITUTE(SUBSTITUTE(SUBSTITUTE(SUBSTITUTE(SUBSTITUTE(SUBSTITUTE(SUBSTITUTE(SUBSTITUTE(SUBSTITUTE(SUBSTITUTE(SUBSTITUTE(DC21,"{会社}",設定!$B$3),"{自分}",設定!$B$4),"{サービス}",設定!$B$5),"{料金}",設定!$B$7),"{日付1}",設定!$B$8),"{日付2}",設定!$B$9),"{時間1}",設定!$B$10),"{時間2}",設定!$B$11),"{時間}","（指定時間）"),"{日付確定}","（確定日）"),"{時間確定}","（確定時間）")) | Y21: =IFERROR(VLOOKUP(DB21,スクリプト_フロー!$A:$F,4,FALSE),"") | Z21: =IF(Y21="","",Y21) | AB21: =IF(DE21="","",SUBSTITUTE(SUBSTITUTE(SUBSTITUTE(SUBSTITUTE(SUBSTITUTE(SUBSTITUTE(SUBSTITUTE(SUBSTITUTE(SUBSTITUTE(SUBSTITUTE(SUBSTITUTE(DE21,"{会社}",設定!$B$3),"{自分}",設定!$B$4),"{サービス}",設定!$B$5),"{料金}",設定!$B$7),"{日付1}",設定!$B$8),"{日付2}",設定!$B$9),"{時間1}",設定!$B$10),"{時間2}",設定!$B$11),"{時間}","（指定時間）"),"{日付確定}","（確定日）"),"{時間確定}","（確定時間）")) | AC21: =IFERROR(VLOOKUP(DD21,スクリプト_フロー!$A:$F,4,FALSE),"") | AD21: =IF(AC21="","",AC21) | AF21: =IF(DG21="","",SUBSTITUTE(SUBSTITUTE(SUBSTITUTE(SUBSTITUTE(SUBSTITUTE(SUBSTITUTE(SUBSTITUTE(SUBSTITUTE(SUBSTITUTE(SUBSTITUTE(SUBSTITUTE(DG21,"{会社}",設定!$B$3),"{自分}",設定!$B$4),"{サービス}",設定!$B$5),"{料金}",設定!$B$7),"{日付1}",設定!$B$8),"{日付2}",設定!$B$9),"{時間1}",設定!$B$10),"{時間2}",設定!$B$11),"{時間}","（指定時間）"),"{日付確定}","（確定日）"),"{時間確定}","（確定時間）")) | AG21: =IFERROR(VLOOKUP(DF21,スクリプト_フロー!$A:$F,4,FALSE),"") | CZ21: =R21&"|"&S21 -> | | DA21: =IFERROR(VLOOKUP(CZ21,スクリプト_フロー!$A:$F,5,FALSE),"") | DB21: =V21&"|"&W21 -> | | DC21: =IFERROR(VLOOKUP(DB21,スクリプト_フロー!$A:$F,5,FALSE),"") | DD21: =Z21&"|"&AA21 -> | | DE21: =IFERROR(VLOOKUP(DD21,スクリプト_フロー!$A:$F,5,FALSE),"") | DF21: =AD21&"|"&AE21 -> | | DG21: =IFERROR(VLOOKUP(DF21,スクリプト_フロー!$A:$F,5,FALSE),"")
A22: 21 | B22: 別府第一ホテル | C22: 0977-24-6311 | D22: 別府駅周辺 | G22: ①架電 | I22: =SUBSTITUTE(SUBSTITUTE(SUBSTITUTE(SUBSTITUTE(SUBSTITUTE(SUBSTITUTE(SUBSTITUTE(SUBSTITUTE(SUBSTITUTE(SUBSTITUTE(SUBSTITUTE(Q22,"{会社}",設定!$B$3),"{自分}",設定!$B$4),"{サービス}",設定!$B$5),"{料金}",設定!$B$7),"{日付1}",設定!$B$8),"{日付2}",設定!$B$9),"{時間1}",設定!$B$10),"{時間2}",設定!$B$11),"{時間}","（指定時間）"),"{日付確定}","（確定日）"),"{時間確定}","（確定時間）") | J22: =IFERROR(VLOOKUP(P22,スクリプト_フロー!$A:$F,4,FALSE),"") | K22: 未架電 | P22: =G22&"|"&H22 -> ①架電| | Q22: =IFERROR(VLOOKUP(P22,スクリプト_フロー!$A:$F,5,FALSE),"") | R22: =IF(J22="","",J22) | T22: =IF(DA22="","",SUBSTITUTE(SUBSTITUTE(SUBSTITUTE(SUBSTITUTE(SUBSTITUTE(SUBSTITUTE(SUBSTITUTE(SUBSTITUTE(SUBSTITUTE(SUBSTITUTE(SUBSTITUTE(DA22,"{会社}",設定!$B$3),"{自分}",設定!$B$4),"{サービス}",設定!$B$5),"{料金}",設定!$B$7),"{日付1}",設定!$B$8),"{日付2}",設定!$B$9),"{時間1}",設定!$B$10),"{時間2}",設定!$B$11),"{時間}","（指定時間）"),"{日付確定}","（確定日）"),"{時間確定}","（確定時間）")) | U22: =IFERROR(VLOOKUP(CZ22,スクリプト_フロー!$A:$F,4,FALSE),"") | V22: =IF(U22="","",U22) | X22: =IF(DC22="","",SUBSTITUTE(SUBSTITUTE(SUBSTITUTE(SUBSTITUTE(SUBSTITUTE(SUBSTITUTE(SUBSTITUTE(SUBSTITUTE(SUBSTITUTE(SUBSTITUTE(SUBSTITUTE(DC22,"{会社}",設定!$B$3),"{自分}",設定!$B$4),"{サービス}",設定!$B$5),"{料金}",設定!$B$7),"{日付1}",設定!$B$8),"{日付2}",設定!$B$9),"{時間1}",設定!$B$10),"{時間2}",設定!$B$11),"{時間}","（指定時間）"),"{日付確定}","（確定日）"),"{時間確定}","（確定時間）")) | Y22: =IFERROR(VLOOKUP(DB22,スクリプト_フロー!$A:$F,4,FALSE),"") | Z22: =IF(Y22="","",Y22) | AB22: =IF(DE22="","",SUBSTITUTE(SUBSTITUTE(SUBSTITUTE(SUBSTITUTE(SUBSTITUTE(SUBSTITUTE(SUBSTITUTE(SUBSTITUTE(SUBSTITUTE(SUBSTITUTE(SUBSTITUTE(DE22,"{会社}",設定!$B$3),"{自分}",設定!$B$4),"{サービス}",設定!$B$5),"{料金}",設定!$B$7),"{日付1}",設定!$B$8),"{日付2}",設定!$B$9),"{時間1}",設定!$B$10),"{時間2}",設定!$B$11),"{時間}","（指定時間）"),"{日付確定}","（確定日）"),"{時間確定}","（確定時間）")) | AC22: =IFERROR(VLOOKUP(DD22,スクリプト_フロー!$A:$F,4,FALSE),"") | AD22: =IF(AC22="","",AC22) | AF22: =IF(DG22="","",SUBSTITUTE(SUBSTITUTE(SUBSTITUTE(SUBSTITUTE(SUBSTITUTE(SUBSTITUTE(SUBSTITUTE(SUBSTITUTE(SUBSTITUTE(SUBSTITUTE(SUBSTITUTE(DG22,"{会社}",設定!$B$3),"{自分}",設定!$B$4),"{サービス}",設定!$B$5),"{料金}",設定!$B$7),"{日付1}",設定!$B$8),"{日付2}",設定!$B$9),"{時間1}",設定!$B$10),"{時間2}",設定!$B$11),"{時間}","（指定時間）"),"{日付確定}","（確定日）"),"{時間確定}","（確定時間）")) | AG22: =IFERROR(VLOOKUP(DF22,スクリプト_フロー!$A:$F,4,FALSE),"") | CZ22: =R22&"|"&S22 -> | | DA22: =IFERROR(VLOOKUP(CZ22,スクリプト_フロー!$A:$F,5,FALSE),"") | DB22: =V22&"|"&W22 -> | | DC22: =IFERROR(VLOOKUP(DB22,スクリプト_フロー!$A:$F,5,FALSE),"") | DD22: =Z22&"|"&AA22 -> | | DE22: =IFERROR(VLOOKUP(DD22,スクリプト_フロー!$A:$F,5,FALSE),"") | DF22: =AD22&"|"&AE22 -> | | DG22: =IFERROR(VLOOKUP(DF22,スクリプト_フロー!$A:$F,5,FALSE),"")
A23: 22 | B23: ホテルアーサー KITAHAMA BASE | C23: 0977-25-2611 | D23: 北浜 | G23: ①架電 | I23: =SUBSTITUTE(SUBSTITUTE(SUBSTITUTE(SUBSTITUTE(SUBSTITUTE(SUBSTITUTE(SUBSTITUTE(SUBSTITUTE(SUBSTITUTE(SUBSTITUTE(SUBSTITUTE(Q23,"{会社}",設定!$B$3),"{自分}",設定!$B$4),"{サービス}",設定!$B$5),"{料金}",設定!$B$7),"{日付1}",設定!$B$8),"{日付2}",設定!$B$9),"{時間1}",設定!$B$10),"{時間2}",設定!$B$11),"{時間}","（指定時間）"),"{日付確定}","（確定日）"),"{時間確定}","（確定時間）") | J23: =IFERROR(VLOOKUP(P23,スクリプト_フロー!$A:$F,4,FALSE),"") | K23: 未架電 | P23: =G23&"|"&H23 -> ①架電| | Q23: =IFERROR(VLOOKUP(P23,スクリプト_フロー!$A:$F,5,FALSE),"") | R23: =IF(J23="","",J23) | T23: =IF(DA23="","",SUBSTITUTE(SUBSTITUTE(SUBSTITUTE(SUBSTITUTE(SUBSTITUTE(SUBSTITUTE(SUBSTITUTE(SUBSTITUTE(SUBSTITUTE(SUBSTITUTE(SUBSTITUTE(DA23,"{会社}",設定!$B$3),"{自分}",設定!$B$4),"{サービス}",設定!$B$5),"{料金}",設定!$B$7),"{日付1}",設定!$B$8),"{日付2}",設定!$B$9),"{時間1}",設定!$B$10),"{時間2}",設定!$B$11),"{時間}","（指定時間）"),"{日付確定}","（確定日）"),"{時間確定}","（確定時間）")) | U23: =IFERROR(VLOOKUP(CZ23,スクリプト_フロー!$A:$F,4,FALSE),"") | V23: =IF(U23="","",U23) | X23: =IF(DC23="","",SUBSTITUTE(SUBSTITUTE(SUBSTITUTE(SUBSTITUTE(SUBSTITUTE(SUBSTITUTE(SUBSTITUTE(SUBSTITUTE(SUBSTITUTE(SUBSTITUTE(SUBSTITUTE(DC23,"{会社}",設定!$B$3),"{自分}",設定!$B$4),"{サービス}",設定!$B$5),"{料金}",設定!$B$7),"{日付1}",設定!$B$8),"{日付2}",設定!$B$9),"{時間1}",設定!$B$10),"{時間2}",設定!$B$11),"{時間}","（指定時間）"),"{日付確定}","（確定日）"),"{時間確定}","（確定時間）")) | Y23: =IFERROR(VLOOKUP(DB23,スクリプト_フロー!$A:$F,4,FALSE),"") | Z23: =IF(Y23="","",Y23) | AB23: =IF(DE23="","",SUBSTITUTE(SUBSTITUTE(SUBSTITUTE(SUBSTITUTE(SUBSTITUTE(SUBSTITUTE(SUBSTITUTE(SUBSTITUTE(SUBSTITUTE(SUBSTITUTE(SUBSTITUTE(DE23,"{会社}",設定!$B$3),"{自分}",設定!$B$4),"{サービス}",設定!$B$5),"{料金}",設定!$B$7),"{日付1}",設定!$B$8),"{日付2}",設定!$B$9),"{時間1}",設定!$B$10),"{時間2}",設定!$B$11),"{時間}","（指定時間）"),"{日付確定}","（確定日）"),"{時間確定}","（確定時間）")) | AC23: =IFERROR(VLOOKUP(DD23,スクリプト_フロー!$A:$F,4,FALSE),"") | AD23: =IF(AC23="","",AC23) | AF23: =IF(DG23="","",SUBSTITUTE(SUBSTITUTE(SUBSTITUTE(SUBSTITUTE(SUBSTITUTE(SUBSTITUTE(SUBSTITUTE(SUBSTITUTE(SUBSTITUTE(SUBSTITUTE(SUBSTITUTE(DG23,"{会社}",設定!$B$3),"{自分}",設定!$B$4),"{サービス}",設定!$B$5),"{料金}",設定!$B$7),"{日付1}",設定!$B$8),"{日付2}",設定!$B$9),"{時間1}",設定!$B$10),"{時間2}",設定!$B$11),"{時間}","（指定時間）"),"{日付確定}","（確定日）"),"{時間確定}","（確定時間）")) | AG23: =IFERROR(VLOOKUP(DF23,スクリプト_フロー!$A:$F,4,FALSE),"") | CZ23: =R23&"|"&S23 -> | | DA23: =IFERROR(VLOOKUP(CZ23,スクリプト_フロー!$A:$F,5,FALSE),"") | DB23: =V23&"|"&W23 -> | | DC23: =IFERROR(VLOOKUP(DB23,スクリプト_フロー!$A:$F,5,FALSE),"") | DD23: =Z23&"|"&AA23 -> | | DE23: =IFERROR(VLOOKUP(DD23,スクリプト_フロー!$A:$F,5,FALSE),"") | DF23: =AD23&"|"&AE23 -> | | DG23: =IFERROR(VLOOKUP(DF23,スクリプト_フロー!$A:$F,5,FALSE),"")
A24: 23 | B24: 別府ホテルエール（HOTEL AILE） | C24: 0977-21-7272 | D24: 北浜 | G24: ①架電 | I24: =SUBSTITUTE(SUBSTITUTE(SUBSTITUTE(SUBSTITUTE(SUBSTITUTE(SUBSTITUTE(SUBSTITUTE(SUBSTITUTE(SUBSTITUTE(SUBSTITUTE(SUBSTITUTE(Q24,"{会社}",設定!$B$3),"{自分}",設定!$B$4),"{サービス}",設定!$B$5),"{料金}",設定!$B$7),"{日付1}",設定!$B$8),"{日付2}",設定!$B$9),"{時間1}",設定!$B$10),"{時間2}",設定!$B$11),"{時間}","（指定時間）"),"{日付確定}","（確定日）"),"{時間確定}","（確定時間）") | J24: =IFERROR(VLOOKUP(P24,スクリプト_フロー!$A:$F,4,FALSE),"") | K24: 未架電 | P24: =G24&"|"&H24 -> ①架電| | Q24: =IFERROR(VLOOKUP(P24,スクリプト_フロー!$A:$F,5,FALSE),"") | R24: =IF(J24="","",J24) | T24: =IF(DA24="","",SUBSTITUTE(SUBSTITUTE(SUBSTITUTE(SUBSTITUTE(SUBSTITUTE(SUBSTITUTE(SUBSTITUTE(SUBSTITUTE(SUBSTITUTE(SUBSTITUTE(SUBSTITUTE(DA24,"{会社}",設定!$B$3),"{自分}",設定!$B$4),"{サービス}",設定!$B$5),"{料金}",設定!$B$7),"{日付1}",設定!$B$8),"{日付2}",設定!$B$9),"{時間1}",設定!$B$10),"{時間2}",設定!$B$11),"{時間}","（指定時間）"),"{日付確定}","（確定日）"),"{時間確定}","（確定時間）")) | U24: =IFERROR(VLOOKUP(CZ24,スクリプト_フロー!$A:$F,4,FALSE),"") | V24: =IF(U24="","",U24) | X24: =IF(DC24="","",SUBSTITUTE(SUBSTITUTE(SUBSTITUTE(SUBSTITUTE(SUBSTITUTE(SUBSTITUTE(SUBSTITUTE(SUBSTITUTE(SUBSTITUTE(SUBSTITUTE(SUBSTITUTE(DC24,"{会社}",設定!$B$3),"{自分}",設定!$B$4),"{サービス}",設定!$B$5),"{料金}",設定!$B$7),"{日付1}",設定!$B$8),"{日付2}",設定!$B$9),"{時間1}",設定!$B$10),"{時間2}",設定!$B$11),"{時間}","（指定時間）"),"{日付確定}","（確定日）"),"{時間確定}","（確定時間）")) | Y24: =IFERROR(VLOOKUP(DB24,スクリプト_フロー!$A:$F,4,FALSE),"") | Z24: =IF(Y24="","",Y24) | AB24: =IF(DE24="","",SUBSTITUTE(SUBSTITUTE(SUBSTITUTE(SUBSTITUTE(SUBSTITUTE(SUBSTITUTE(SUBSTITUTE(SUBSTITUTE(SUBSTITUTE(SUBSTITUTE(SUBSTITUTE(DE24,"{会社}",設定!$B$3),"{自分}",設定!$B$4),"{サービス}",設定!$B$5),"{料金}",設定!$B$7),"{日付1}",設定!$B$8),"{日付2}",設定!$B$9),"{時間1}",設定!$B$10),"{時間2}",設定!$B$11),"{時間}","（指定時間）"),"{日付確定}","（確定日）"),"{時間確定}","（確定時間）")) | AC24: =IFERROR(VLOOKUP(DD24,スクリプト_フロー!$A:$F,4,FALSE),"") | AD24: =IF(AC24="","",AC24) | AF24: =IF(DG24="","",SUBSTITUTE(SUBSTITUTE(SUBSTITUTE(SUBSTITUTE(SUBSTITUTE(SUBSTITUTE(SUBSTITUTE(SUBSTITUTE(SUBSTITUTE(SUBSTITUTE(SUBSTITUTE(DG24,"{会社}",設定!$B$3),"{自分}",設定!$B$4),"{サービス}",設定!$B$5),"{料金}",設定!$B$7),"{日付1}",設定!$B$8),"{日付2}",設定!$B$9),"{時間1}",設定!$B$10),"{時間2}",設定!$B$11),"{時間}","（指定時間）"),"{日付確定}","（確定日）"),"{時間確定}","（確定時間）")) | AG24: =IFERROR(VLOOKUP(DF24,スクリプト_フロー!$A:$F,4,FALSE),"") | CZ24: =R24&"|"&S24 -> | | DA24: =IFERROR(VLOOKUP(CZ24,スクリプト_フロー!$A:$F,5,FALSE),"") | DB24: =V24&"|"&W24 -> | | DC24: =IFERROR(VLOOKUP(DB24,スクリプト_フロー!$A:$F,5,FALSE),"") | DD24: =Z24&"|"&AA24 -> | | DE24: =IFERROR(VLOOKUP(DD24,スクリプト_フロー!$A:$F,5,FALSE),"") | DF24: =AD24&"|"&AE24 -> | | DG24: =IFERROR(VLOOKUP(DF24,スクリプト_フロー!$A:$F,5,FALSE),"")
A25: 24 | B25: ホテルなぎさ | C25: 0977-23-8101 | D25: 北浜 | G25: ①架電 | I25: =SUBSTITUTE(SUBSTITUTE(SUBSTITUTE(SUBSTITUTE(SUBSTITUTE(SUBSTITUTE(SUBSTITUTE(SUBSTITUTE(SUBSTITUTE(SUBSTITUTE(SUBSTITUTE(Q25,"{会社}",設定!$B$3),"{自分}",設定!$B$4),"{サービス}",設定!$B$5),"{料金}",設定!$B$7),"{日付1}",設定!$B$8),"{日付2}",設定!$B$9),"{時間1}",設定!$B$10),"{時間2}",設定!$B$11),"{時間}","（指定時間）"),"{日付確定}","（確定日）"),"{時間確定}","（確定時間）") | J25: =IFERROR(VLOOKUP(P25,スクリプト_フロー!$A:$F,4,FALSE),"") | K25: 未架電 | P25: =G25&"|"&H25 -> ①架電| | Q25: =IFERROR(VLOOKUP(P25,スクリプト_フロー!$A:$F,5,FALSE),"") | R25: =IF(J25="","",J25) | T25: =IF(DA25="","",SUBSTITUTE(SUBSTITUTE(SUBSTITUTE(SUBSTITUTE(SUBSTITUTE(SUBSTITUTE(SUBSTITUTE(SUBSTITUTE(SUBSTITUTE(SUBSTITUTE(SUBSTITUTE(DA25,"{会社}",設定!$B$3),"{自分}",設定!$B$4),"{サービス}",設定!$B$5),"{料金}",設定!$B$7),"{日付1}",設定!$B$8),"{日付2}",設定!$B$9),"{時間1}",設定!$B$10),"{時間2}",設定!$B$11),"{時間}","（指定時間）"),"{日付確定}","（確定日）"),"{時間確定}","（確定時間）")) | U25: =IFERROR(VLOOKUP(CZ25,スクリプト_フロー!$A:$F,4,FALSE),"") | V25: =IF(U25="","",U25) | X25: =IF(DC25="","",SUBSTITUTE(SUBSTITUTE(SUBSTITUTE(SUBSTITUTE(SUBSTITUTE(SUBSTITUTE(SUBSTITUTE(SUBSTITUTE(SUBSTITUTE(SUBSTITUTE(SUBSTITUTE(DC25,"{会社}",設定!$B$3),"{自分}",設定!$B$4),"{サービス}",設定!$B$5),"{料金}",設定!$B$7),"{日付1}",設定!$B$8),"{日付2}",設定!$B$9),"{時間1}",設定!$B$10),"{時間2}",設定!$B$11),"{時間}","（指定時間）"),"{日付確定}","（確定日）"),"{時間確定}","（確定時間）")) | Y25: =IFERROR(VLOOKUP(DB25,スクリプト_フロー!$A:$F,4,FALSE),"") | Z25: =IF(Y25="","",Y25) | AB25: =IF(DE25="","",SUBSTITUTE(SUBSTITUTE(SUBSTITUTE(SUBSTITUTE(SUBSTITUTE(SUBSTITUTE(SUBSTITUTE(SUBSTITUTE(SUBSTITUTE(SUBSTITUTE(SUBSTITUTE(DE25,"{会社}",設定!$B$3),"{自分}",設定!$B$4),"{サービス}",設定!$B$5),"{料金}",設定!$B$7),"{日付1}",設定!$B$8),"{日付2}",設定!$B$9),"{時間1}",設定!$B$10),"{時間2}",設定!$B$11),"{時間}","（指定時間）"),"{日付確定}","（確定日）"),"{時間確定}","（確定時間）")) | AC25: =IFERROR(VLOOKUP(DD25,スクリプト_フロー!$A:$F,4,FALSE),"") | AD25: =IF(AC25="","",AC25) | AF25: =IF(DG25="","",SUBSTITUTE(SUBSTITUTE(SUBSTITUTE(SUBSTITUTE(SUBSTITUTE(SUBSTITUTE(SUBSTITUTE(SUBSTITUTE(SUBSTITUTE(SUBSTITUTE(SUBSTITUTE(DG25,"{会社}",設定!$B$3),"{自分}",設定!$B$4),"{サービス}",設定!$B$5),"{料金}",設定!$B$7),"{日付1}",設定!$B$8),"{日付2}",設定!$B$9),"{時間1}",設定!$B$10),"{時間2}",設定!$B$11),"{時間}","（指定時間）"),"{日付確定}","（確定日）"),"{時間確定}","（確定時間）")) | AG25: =IFERROR(VLOOKUP(DF25,スクリプト_フロー!$A:$F,4,FALSE),"") | CZ25: =R25&"|"&S25 -> | | DA25: =IFERROR(VLOOKUP(CZ25,スクリプト_フロー!$A:$F,5,FALSE),"") | DB25: =V25&"|"&W25 -> | | DC25: =IFERROR(VLOOKUP(DB25,スクリプト_フロー!$A:$F,5,FALSE),"") | DD25: =Z25&"|"&AA25 -> | | DE25: =IFERROR(VLOOKUP(DD25,スクリプト_フロー!$A:$F,5,FALSE),"") | DF25: =AD25&"|"&AE25 -> | | DG25: =IFERROR(VLOOKUP(DF25,スクリプト_フロー!$A:$F,5,FALSE),"")
A26: 25 | B26: ジェイホッパーズ別府ゲストハウス | C26: 0977-26-1700 | D26: 的ヶ浜 | G26: ①架電 | I26: =SUBSTITUTE(SUBSTITUTE(SUBSTITUTE(SUBSTITUTE(SUBSTITUTE(SUBSTITUTE(SUBSTITUTE(SUBSTITUTE(SUBSTITUTE(SUBSTITUTE(SUBSTITUTE(Q26,"{会社}",設定!$B$3),"{自分}",設定!$B$4),"{サービス}",設定!$B$5),"{料金}",設定!$B$7),"{日付1}",設定!$B$8),"{日付2}",設定!$B$9),"{時間1}",設定!$B$10),"{時間2}",設定!$B$11),"{時間}","（指定時間）"),"{日付確定}","（確定日）"),"{時間確定}","（確定時間）") | J26: =IFERROR(VLOOKUP(P26,スクリプト_フロー!$A:$F,4,FALSE),"") | K26: 未架電 | P26: =G26&"|"&H26 -> ①架電| | Q26: =IFERROR(VLOOKUP(P26,スクリプト_フロー!$A:$F,5,FALSE),"") | R26: =IF(J26="","",J26) | T26: =IF(DA26="","",SUBSTITUTE(SUBSTITUTE(SUBSTITUTE(SUBSTITUTE(SUBSTITUTE(SUBSTITUTE(SUBSTITUTE(SUBSTITUTE(SUBSTITUTE(SUBSTITUTE(SUBSTITUTE(DA26,"{会社}",設定!$B$3),"{自分}",設定!$B$4),"{サービス}",設定!$B$5),"{料金}",設定!$B$7),"{日付1}",設定!$B$8),"{日付2}",設定!$B$9),"{時間1}",設定!$B$10),"{時間2}",設定!$B$11),"{時間}","（指定時間）"),"{日付確定}","（確定日）"),"{時間確定}","（確定時間）")) | U26: =IFERROR(VLOOKUP(CZ26,スクリプト_フロー!$A:$F,4,FALSE),"") | V26: =IF(U26="","",U26) | X26: =IF(DC26="","",SUBSTITUTE(SUBSTITUTE(SUBSTITUTE(SUBSTITUTE(SUBSTITUTE(SUBSTITUTE(SUBSTITUTE(SUBSTITUTE(SUBSTITUTE(SUBSTITUTE(SUBSTITUTE(DC26,"{会社}",設定!$B$3),"{自分}",設定!$B$4),"{サービス}",設定!$B$5),"{料金}",設定!$B$7),"{日付1}",設定!$B$8),"{日付2}",設定!$B$9),"{時間1}",設定!$B$10),"{時間2}",設定!$B$11),"{時間}","（指定時間）"),"{日付確定}","（確定日）"),"{時間確定}","（確定時間）")) | Y26: =IFERROR(VLOOKUP(DB26,スクリプト_フロー!$A:$F,4,FALSE),"") | Z26: =IF(Y26="","",Y26) | AB26: =IF(DE26="","",SUBSTITUTE(SUBSTITUTE(SUBSTITUTE(SUBSTITUTE(SUBSTITUTE(SUBSTITUTE(SUBSTITUTE(SUBSTITUTE(SUBSTITUTE(SUBSTITUTE(SUBSTITUTE(DE26,"{会社}",設定!$B$3),"{自分}",設定!$B$4),"{サービス}",設定!$B$5),"{料金}",設定!$B$7),"{日付1}",設定!$B$8),"{日付2}",設定!$B$9),"{時間1}",設定!$B$10),"{時間2}",設定!$B$11),"{時間}","（指定時間）"),"{日付確定}","（確定日）"),"{時間確定}","（確定時間）")) | AC26: =IFERROR(VLOOKUP(DD26,スクリプト_フロー!$A:$F,4,FALSE),"") | AD26: =IF(AC26="","",AC26) | AF26: =IF(DG26="","",SUBSTITUTE(SUBSTITUTE(SUBSTITUTE(SUBSTITUTE(SUBSTITUTE(SUBSTITUTE(SUBSTITUTE(SUBSTITUTE(SUBSTITUTE(SUBSTITUTE(SUBSTITUTE(DG26,"{会社}",設定!$B$3),"{自分}",設定!$B$4),"{サービス}",設定!$B$5),"{料金}",設定!$B$7),"{日付1}",設定!$B$8),"{日付2}",設定!$B$9),"{時間1}",設定!$B$10),"{時間2}",設定!$B$11),"{時間}","（指定時間）"),"{日付確定}","（確定日）"),"{時間確定}","（確定時間）")) | AG26: =IFERROR(VLOOKUP(DF26,スクリプト_フロー!$A:$F,4,FALSE),"") | CZ26: =R26&"|"&S26 -> | | DA26: =IFERROR(VLOOKUP(CZ26,スクリプト_フロー!$A:$F,5,FALSE),"") | DB26: =V26&"|"&W26 -> | | DC26: =IFERROR(VLOOKUP(DB26,スクリプト_フロー!$A:$F,5,FALSE),"") | DD26: =Z26&"|"&AA26 -> | | DE26: =IFERROR(VLOOKUP(DD26,スクリプト_フロー!$A:$F,5,FALSE),"") | DF26: =AD26&"|"&AE26 -> | | DG26: =IFERROR(VLOOKUP(DF26,スクリプト_フロー!$A:$F,5,FALSE),"")
A27: 26 | B27: ホテルニューツルタ | C27: 0977-22-1110 | D27: 北浜 | G27: ①架電 | I27: =SUBSTITUTE(SUBSTITUTE(SUBSTITUTE(SUBSTITUTE(SUBSTITUTE(SUBSTITUTE(SUBSTITUTE(SUBSTITUTE(SUBSTITUTE(SUBSTITUTE(SUBSTITUTE(Q27,"{会社}",設定!$B$3),"{自分}",設定!$B$4),"{サービス}",設定!$B$5),"{料金}",設定!$B$7),"{日付1}",設定!$B$8),"{日付2}",設定!$B$9),"{時間1}",設定!$B$10),"{時間2}",設定!$B$11),"{時間}","（指定時間）"),"{日付確定}","（確定日）"),"{時間確定}","（確定時間）") | J27: =IFERROR(VLOOKUP(P27,スクリプト_フロー!$A:$F,4,FALSE),"") | K27: 未架電 | P27: =G27&"|"&H27 -> ①架電| | Q27: =IFERROR(VLOOKUP(P27,スクリプト_フロー!$A:$F,5,FALSE),"") | R27: =IF(J27="","",J27) | T27: =IF(DA27="","",SUBSTITUTE(SUBSTITUTE(SUBSTITUTE(SUBSTITUTE(SUBSTITUTE(SUBSTITUTE(SUBSTITUTE(SUBSTITUTE(SUBSTITUTE(SUBSTITUTE(SUBSTITUTE(DA27,"{会社}",設定!$B$3),"{自分}",設定!$B$4),"{サービス}",設定!$B$5),"{料金}",設定!$B$7),"{日付1}",設定!$B$8),"{日付2}",設定!$B$9),"{時間1}",設定!$B$10),"{時間2}",設定!$B$11),"{時間}","（指定時間）"),"{日付確定}","（確定日）"),"{時間確定}","（確定時間）")) | U27: =IFERROR(VLOOKUP(CZ27,スクリプト_フロー!$A:$F,4,FALSE),"") | V27: =IF(U27="","",U27) | X27: =IF(DC27="","",SUBSTITUTE(SUBSTITUTE(SUBSTITUTE(SUBSTITUTE(SUBSTITUTE(SUBSTITUTE(SUBSTITUTE(SUBSTITUTE(SUBSTITUTE(SUBSTITUTE(SUBSTITUTE(DC27,"{会社}",設定!$B$3),"{自分}",設定!$B$4),"{サービス}",設定!$B$5),"{料金}",設定!$B$7),"{日付1}",設定!$B$8),"{日付2}",設定!$B$9),"{時間1}",設定!$B$10),"{時間2}",設定!$B$11),"{時間}","（指定時間）"),"{日付確定}","（確定日）"),"{時間確定}","（確定時間）")) | Y27: =IFERROR(VLOOKUP(DB27,スクリプト_フロー!$A:$F,4,FALSE),"") | Z27: =IF(Y27="","",Y27) | AB27: =IF(DE27="","",SUBSTITUTE(SUBSTITUTE(SUBSTITUTE(SUBSTITUTE(SUBSTITUTE(SUBSTITUTE(SUBSTITUTE(SUBSTITUTE(SUBSTITUTE(SUBSTITUTE(SUBSTITUTE(DE27,"{会社}",設定!$B$3),"{自分}",設定!$B$4),"{サービス}",設定!$B$5),"{料金}",設定!$B$7),"{日付1}",設定!$B$8),"{日付2}",設定!$B$9),"{時間1}",設定!$B$10),"{時間2}",設定!$B$11),"{時間}","（指定時間）"),"{日付確定}","（確定日）"),"{時間確定}","（確定時間）")) | AC27: =IFERROR(VLOOKUP(DD27,スクリプト_フロー!$A:$F,4,FALSE),"") | AD27: =IF(AC27="","",AC27) | AF27: =IF(DG27="","",SUBSTITUTE(SUBSTITUTE(SUBSTITUTE(SUBSTITUTE(SUBSTITUTE(SUBSTITUTE(SUBSTITUTE(SUBSTITUTE(SUBSTITUTE(SUBSTITUTE(SUBSTITUTE(DG27,"{会社}",設定!$B$3),"{自分}",設定!$B$4),"{サービス}",設定!$B$5),"{料金}",設定!$B$7),"{日付1}",設定!$B$8),"{日付2}",設定!$B$9),"{時間1}",設定!$B$10),"{時間2}",設定!$B$11),"{時間}","（指定時間）"),"{日付確定}","（確定日）"),"{時間確定}","（確定時間）")) | AG27: =IFERROR(VLOOKUP(DF27,スクリプト_フロー!$A:$F,4,FALSE),"") | CZ27: =R27&"|"&S27 -> | | DA27: =IFERROR(VLOOKUP(CZ27,スクリプト_フロー!$A:$F,5,FALSE),"") | DB27: =V27&"|"&W27 -> | | DC27: =IFERROR(VLOOKUP(DB27,スクリプト_フロー!$A:$F,5,FALSE),"") | DD27: =Z27&"|"&AA27 -> | | DE27: =IFERROR(VLOOKUP(DD27,スクリプト_フロー!$A:$F,5,FALSE),"") | DF27: =AD27&"|"&AE27 -> | | DG27: =IFERROR(VLOOKUP(DF27,スクリプト_フロー!$A:$F,5,FALSE),"")
A28: 27 | B28: 別府温泉 海乃ホテルはじめ（旧ホテルニュー松実） | C28: 0977-23-2201 | D28: 北浜 | G28: ①架電 | I28: =SUBSTITUTE(SUBSTITUTE(SUBSTITUTE(SUBSTITUTE(SUBSTITUTE(SUBSTITUTE(SUBSTITUTE(SUBSTITUTE(SUBSTITUTE(SUBSTITUTE(SUBSTITUTE(Q28,"{会社}",設定!$B$3),"{自分}",設定!$B$4),"{サービス}",設定!$B$5),"{料金}",設定!$B$7),"{日付1}",設定!$B$8),"{日付2}",設定!$B$9),"{時間1}",設定!$B$10),"{時間2}",設定!$B$11),"{時間}","（指定時間）"),"{日付確定}","（確定日）"),"{時間確定}","（確定時間）") | J28: =IFERROR(VLOOKUP(P28,スクリプト_フロー!$A:$F,4,FALSE),"") | K28: 未架電 | P28: =G28&"|"&H28 -> ①架電| | Q28: =IFERROR(VLOOKUP(P28,スクリプト_フロー!$A:$F,5,FALSE),"") | R28: =IF(J28="","",J28) | T28: =IF(DA28="","",SUBSTITUTE(SUBSTITUTE(SUBSTITUTE(SUBSTITUTE(SUBSTITUTE(SUBSTITUTE(SUBSTITUTE(SUBSTITUTE(SUBSTITUTE(SUBSTITUTE(SUBSTITUTE(DA28,"{会社}",設定!$B$3),"{自分}",設定!$B$4),"{サービス}",設定!$B$5),"{料金}",設定!$B$7),"{日付1}",設定!$B$8),"{日付2}",設定!$B$9),"{時間1}",設定!$B$10),"{時間2}",設定!$B$11),"{時間}","（指定時間）"),"{日付確定}","（確定日）"),"{時間確定}","（確定時間）")) | U28: =IFERROR(VLOOKUP(CZ28,スクリプト_フロー!$A:$F,4,FALSE),"") | V28: =IF(U28="","",U28) | X28: =IF(DC28="","",SUBSTITUTE(SUBSTITUTE(SUBSTITUTE(SUBSTITUTE(SUBSTITUTE(SUBSTITUTE(SUBSTITUTE(SUBSTITUTE(SUBSTITUTE(SUBSTITUTE(SUBSTITUTE(DC28,"{会社}",設定!$B$3),"{自分}",設定!$B$4),"{サービス}",設定!$B$5),"{料金}",設定!$B$7),"{日付1}",設定!$B$8),"{日付2}",設定!$B$9),"{時間1}",設定!$B$10),"{時間2}",設定!$B$11),"{時間}","（指定時間）"),"{日付確定}","（確定日）"),"{時間確定}","（確定時間）")) | Y28: =IFERROR(VLOOKUP(DB28,スクリプト_フロー!$A:$F,4,FALSE),"") | Z28: =IF(Y28="","",Y28) | AB28: =IF(DE28="","",SUBSTITUTE(SUBSTITUTE(SUBSTITUTE(SUBSTITUTE(SUBSTITUTE(SUBSTITUTE(SUBSTITUTE(SUBSTITUTE(SUBSTITUTE(SUBSTITUTE(SUBSTITUTE(DE28,"{会社}",設定!$B$3),"{自分}",設定!$B$4),"{サービス}",設定!$B$5),"{料金}",設定!$B$7),"{日付1}",設定!$B$8),"{日付2}",設定!$B$9),"{時間1}",設定!$B$10),"{時間2}",設定!$B$11),"{時間}","（指定時間）"),"{日付確定}","（確定日）"),"{時間確定}","（確定時間）")) | AC28: =IFERROR(VLOOKUP(DD28,スクリプト_フロー!$A:$F,4,FALSE),"") | AD28: =IF(AC28="","",AC28) | AF28: =IF(DG28="","",SUBSTITUTE(SUBSTITUTE(SUBSTITUTE(SUBSTITUTE(SUBSTITUTE(SUBSTITUTE(SUBSTITUTE(SUBSTITUTE(SUBSTITUTE(SUBSTITUTE(SUBSTITUTE(DG28,"{会社}",設定!$B$3),"{自分}",設定!$B$4),"{サービス}",設定!$B$5),"{料金}",設定!$B$7),"{日付1}",設定!$B$8),"{日付2}",設定!$B$9),"{時間1}",設定!$B$10),"{時間2}",設定!$B$11),"{時間}","（指定時間）"),"{日付確定}","（確定日）"),"{時間確定}","（確定時間）")) | AG28: =IFERROR(VLOOKUP(DF28,スクリプト_フロー!$A:$F,4,FALSE),"") | CZ28: =R28&"|"&S28 -> | | DA28: =IFERROR(VLOOKUP(CZ28,スクリプト_フロー!$A:$F,5,FALSE),"") | DB28: =V28&"|"&W28 -> | | DC28: =IFERROR(VLOOKUP(DB28,スクリプト_フロー!$A:$F,5,FALSE),"") | DD28: =Z28&"|"&AA28 -> | | DE28: =IFERROR(VLOOKUP(DD28,スクリプト_フロー!$A:$F,5,FALSE),"") | DF28: =AD28&"|"&AE28 -> | | DG28: =IFERROR(VLOOKUP(DF28,スクリプト_フロー!$A:$F,5,FALSE),"")
A29: 28 | B29: 別館うみね | C29: 050-5799-8508 | D29: 鉄輪 | G29: ①架電 | I29: =SUBSTITUTE(SUBSTITUTE(SUBSTITUTE(SUBSTITUTE(SUBSTITUTE(SUBSTITUTE(SUBSTITUTE(SUBSTITUTE(SUBSTITUTE(SUBSTITUTE(SUBSTITUTE(Q29,"{会社}",設定!$B$3),"{自分}",設定!$B$4),"{サービス}",設定!$B$5),"{料金}",設定!$B$7),"{日付1}",設定!$B$8),"{日付2}",設定!$B$9),"{時間1}",設定!$B$10),"{時間2}",設定!$B$11),"{時間}","（指定時間）"),"{日付確定}","（確定日）"),"{時間確定}","（確定時間）") | J29: =IFERROR(VLOOKUP(P29,スクリプト_フロー!$A:$F,4,FALSE),"") | K29: 未架電 | P29: =G29&"|"&H29 -> ①架電| | Q29: =IFERROR(VLOOKUP(P29,スクリプト_フロー!$A:$F,5,FALSE),"") | R29: =IF(J29="","",J29) | T29: =IF(DA29="","",SUBSTITUTE(SUBSTITUTE(SUBSTITUTE(SUBSTITUTE(SUBSTITUTE(SUBSTITUTE(SUBSTITUTE(SUBSTITUTE(SUBSTITUTE(SUBSTITUTE(SUBSTITUTE(DA29,"{会社}",設定!$B$3),"{自分}",設定!$B$4),"{サービス}",設定!$B$5),"{料金}",設定!$B$7),"{日付1}",設定!$B$8),"{日付2}",設定!$B$9),"{時間1}",設定!$B$10),"{時間2}",設定!$B$11),"{時間}","（指定時間）"),"{日付確定}","（確定日）"),"{時間確定}","（確定時間）")) | U29: =IFERROR(VLOOKUP(CZ29,スクリプト_フロー!$A:$F,4,FALSE),"") | V29: =IF(U29="","",U29) | X29: =IF(DC29="","",SUBSTITUTE(SUBSTITUTE(SUBSTITUTE(SUBSTITUTE(SUBSTITUTE(SUBSTITUTE(SUBSTITUTE(SUBSTITUTE(SUBSTITUTE(SUBSTITUTE(SUBSTITUTE(DC29,"{会社}",設定!$B$3),"{自分}",設定!$B$4),"{サービス}",設定!$B$5),"{料金}",設定!$B$7),"{日付1}",設定!$B$8),"{日付2}",設定!$B$9),"{時間1}",設定!$B$10),"{時間2}",設定!$B$11),"{時間}","（指定時間）"),"{日付確定}","（確定日）"),"{時間確定}","（確定時間）")) | Y29: =IFERROR(VLOOKUP(DB29,スクリプト_フロー!$A:$F,4,FALSE),"") | Z29: =IF(Y29="","",Y29) | AB29: =IF(DE29="","",SUBSTITUTE(SUBSTITUTE(SUBSTITUTE(SUBSTITUTE(SUBSTITUTE(SUBSTITUTE(SUBSTITUTE(SUBSTITUTE(SUBSTITUTE(SUBSTITUTE(SUBSTITUTE(DE29,"{会社}",設定!$B$3),"{自分}",設定!$B$4),"{サービス}",設定!$B$5),"{料金}",設定!$B$7),"{日付1}",設定!$B$8),"{日付2}",設定!$B$9),"{時間1}",設定!$B$10),"{時間2}",設定!$B$11),"{時間}","（指定時間）"),"{日付確定}","（確定日）"),"{時間確定}","（確定時間）")) | AC29: =IFERROR(VLOOKUP(DD29,スクリプト_フロー!$A:$F,4,FALSE),"") | AD29: =IF(AC29="","",AC29) | AF29: =IF(DG29="","",SUBSTITUTE(SUBSTITUTE(SUBSTITUTE(SUBSTITUTE(SUBSTITUTE(SUBSTITUTE(SUBSTITUTE(SUBSTITUTE(SUBSTITUTE(SUBSTITUTE(SUBSTITUTE(DG29,"{会社}",設定!$B$3),"{自分}",設定!$B$4),"{サービス}",設定!$B$5),"{料金}",設定!$B$7),"{日付1}",設定!$B$8),"{日付2}",設定!$B$9),"{時間1}",設定!$B$10),"{時間2}",設定!$B$11),"{時間}","（指定時間）"),"{日付確定}","（確定日）"),"{時間確定}","（確定時間）")) | AG29: =IFERROR(VLOOKUP(DF29,スクリプト_フロー!$A:$F,4,FALSE),"") | CZ29: =R29&"|"&S29 -> | | DA29: =IFERROR(VLOOKUP(CZ29,スクリプト_フロー!$A:$F,5,FALSE),"") | DB29: =V29&"|"&W29 -> | | DC29: =IFERROR(VLOOKUP(DB29,スクリプト_フロー!$A:$F,5,FALSE),"") | DD29: =Z29&"|"&AA29 -> | | DE29: =IFERROR(VLOOKUP(DD29,スクリプト_フロー!$A:$F,5,FALSE),"") | DF29: =AD29&"|"&AE29 -> | | DG29: =IFERROR(VLOOKUP(DF29,スクリプト_フロー!$A:$F,5,FALSE),"")
A30: 29 | B30: ホテルうみね | C30: 0977-26-0002 | D30: 北浜 | G30: ①架電 | I30: =SUBSTITUTE(SUBSTITUTE(SUBSTITUTE(SUBSTITUTE(SUBSTITUTE(SUBSTITUTE(SUBSTITUTE(SUBSTITUTE(SUBSTITUTE(SUBSTITUTE(SUBSTITUTE(Q30,"{会社}",設定!$B$3),"{自分}",設定!$B$4),"{サービス}",設定!$B$5),"{料金}",設定!$B$7),"{日付1}",設定!$B$8),"{日付2}",設定!$B$9),"{時間1}",設定!$B$10),"{時間2}",設定!$B$11),"{時間}","（指定時間）"),"{日付確定}","（確定日）"),"{時間確定}","（確定時間）") | J30: =IFERROR(VLOOKUP(P30,スクリプト_フロー!$A:$F,4,FALSE),"") | K30: 未架電 | P30: =G30&"|"&H30 -> ①架電| | Q30: =IFERROR(VLOOKUP(P30,スクリプト_フロー!$A:$F,5,FALSE),"") | R30: =IF(J30="","",J30) | T30: =IF(DA30="","",SUBSTITUTE(SUBSTITUTE(SUBSTITUTE(SUBSTITUTE(SUBSTITUTE(SUBSTITUTE(SUBSTITUTE(SUBSTITUTE(SUBSTITUTE(SUBSTITUTE(SUBSTITUTE(DA30,"{会社}",設定!$B$3),"{自分}",設定!$B$4),"{サービス}",設定!$B$5),"{料金}",設定!$B$7),"{日付1}",設定!$B$8),"{日付2}",設定!$B$9),"{時間1}",設定!$B$10),"{時間2}",設定!$B$11),"{時間}","（指定時間）"),"{日付確定}","（確定日）"),"{時間確定}","（確定時間）")) | U30: =IFERROR(VLOOKUP(CZ30,スクリプト_フロー!$A:$F,4,FALSE),"") | V30: =IF(U30="","",U30) | X30: =IF(DC30="","",SUBSTITUTE(SUBSTITUTE(SUBSTITUTE(SUBSTITUTE(SUBSTITUTE(SUBSTITUTE(SUBSTITUTE(SUBSTITUTE(SUBSTITUTE(SUBSTITUTE(SUBSTITUTE(DC30,"{会社}",設定!$B$3),"{自分}",設定!$B$4),"{サービス}",設定!$B$5),"{料金}",設定!$B$7),"{日付1}",設定!$B$8),"{日付2}",設定!$B$9),"{時間1}",設定!$B$10),"{時間2}",設定!$B$11),"{時間}","（指定時間）"),"{日付確定}","（確定日）"),"{時間確定}","（確定時間）")) | Y30: =IFERROR(VLOOKUP(DB30,スクリプト_フロー!$A:$F,4,FALSE),"") | Z30: =IF(Y30="","",Y30) | AB30: =IF(DE30="","",SUBSTITUTE(SUBSTITUTE(SUBSTITUTE(SUBSTITUTE(SUBSTITUTE(SUBSTITUTE(SUBSTITUTE(SUBSTITUTE(SUBSTITUTE(SUBSTITUTE(SUBSTITUTE(DE30,"{会社}",設定!$B$3),"{自分}",設定!$B$4),"{サービス}",設定!$B$5),"{料金}",設定!$B$7),"{日付1}",設定!$B$8),"{日付2}",設定!$B$9),"{時間1}",設定!$B$10),"{時間2}",設定!$B$11),"{時間}","（指定時間）"),"{日付確定}","（確定日）"),"{時間確定}","（確定時間）")) | AC30: =IFERROR(VLOOKUP(DD30,スクリプト_フロー!$A:$F,4,FALSE),"") | AD30: =IF(AC30="","",AC30) | AF30: =IF(DG30="","",SUBSTITUTE(SUBSTITUTE(SUBSTITUTE(SUBSTITUTE(SUBSTITUTE(SUBSTITUTE(SUBSTITUTE(SUBSTITUTE(SUBSTITUTE(SUBSTITUTE(SUBSTITUTE(DG30,"{会社}",設定!$B$3),"{自分}",設定!$B$4),"{サービス}",設定!$B$5),"{料金}",設定!$B$7),"{日付1}",設定!$B$8),"{日付2}",設定!$B$9),"{時間1}",設定!$B$10),"{時間2}",設定!$B$11),"{時間}","（指定時間）"),"{日付確定}","（確定日）"),"{時間確定}","（確定時間）")) | AG30: =IFERROR(VLOOKUP(DF30,スクリプト_フロー!$A:$F,4,FALSE),"") | CZ30: =R30&"|"&S30 -> | | DA30: =IFERROR(VLOOKUP(CZ30,スクリプト_フロー!$A:$F,5,FALSE),"") | DB30: =V30&"|"&W30 -> | | DC30: =IFERROR(VLOOKUP(DB30,スクリプト_フロー!$A:$F,5,FALSE),"") | DD30: =Z30&"|"&AA30 -> | | DE30: =IFERROR(VLOOKUP(DD30,スクリプト_フロー!$A:$F,5,FALSE),"") | DF30: =AD30&"|"&AE30 -> | | DG30: =IFERROR(VLOOKUP(DF30,スクリプト_フロー!$A:$F,5,FALSE),"")
A31: 30 | B31: 海薫る宿ホテルニュー松実 | C31: 0977-23-2201 | D31: 北浜/別府駅周辺 | G31: ①架電 | I31: =SUBSTITUTE(SUBSTITUTE(SUBSTITUTE(SUBSTITUTE(SUBSTITUTE(SUBSTITUTE(SUBSTITUTE(SUBSTITUTE(SUBSTITUTE(SUBSTITUTE(SUBSTITUTE(Q31,"{会社}",設定!$B$3),"{自分}",設定!$B$4),"{サービス}",設定!$B$5),"{料金}",設定!$B$7),"{日付1}",設定!$B$8),"{日付2}",設定!$B$9),"{時間1}",設定!$B$10),"{時間2}",設定!$B$11),"{時間}","（指定時間）"),"{日付確定}","（確定日）"),"{時間確定}","（確定時間）") | J31: =IFERROR(VLOOKUP(P31,スクリプト_フロー!$A:$F,4,FALSE),"") | K31: 未架電 | P31: =G31&"|"&H31 -> ①架電| | Q31: =IFERROR(VLOOKUP(P31,スクリプト_フロー!$A:$F,5,FALSE),"") | R31: =IF(J31="","",J31) | T31: =IF(DA31="","",SUBSTITUTE(SUBSTITUTE(SUBSTITUTE(SUBSTITUTE(SUBSTITUTE(SUBSTITUTE(SUBSTITUTE(SUBSTITUTE(SUBSTITUTE(SUBSTITUTE(SUBSTITUTE(DA31,"{会社}",設定!$B$3),"{自分}",設定!$B$4),"{サービス}",設定!$B$5),"{料金}",設定!$B$7),"{日付1}",設定!$B$8),"{日付2}",設定!$B$9),"{時間1}",設定!$B$10),"{時間2}",設定!$B$11),"{時間}","（指定時間）"),"{日付確定}","（確定日）"),"{時間確定}","（確定時間）")) | U31: =IFERROR(VLOOKUP(CZ31,スクリプト_フロー!$A:$F,4,FALSE),"") | V31: =IF(U31="","",U31) | X31: =IF(DC31="","",SUBSTITUTE(SUBSTITUTE(SUBSTITUTE(SUBSTITUTE(SUBSTITUTE(SUBSTITUTE(SUBSTITUTE(SUBSTITUTE(SUBSTITUTE(SUBSTITUTE(SUBSTITUTE(DC31,"{会社}",設定!$B$3),"{自分}",設定!$B$4),"{サービス}",設定!$B$5),"{料金}",設定!$B$7),"{日付1}",設定!$B$8),"{日付2}",設定!$B$9),"{時間1}",設定!$B$10),"{時間2}",設定!$B$11),"{時間}","（指定時間）"),"{日付確定}","（確定日）"),"{時間確定}","（確定時間）")) | Y31: =IFERROR(VLOOKUP(DB31,スクリプト_フロー!$A:$F,4,FALSE),"") | Z31: =IF(Y31="","",Y31) | AB31: =IF(DE31="","",SUBSTITUTE(SUBSTITUTE(SUBSTITUTE(SUBSTITUTE(SUBSTITUTE(SUBSTITUTE(SUBSTITUTE(SUBSTITUTE(SUBSTITUTE(SUBSTITUTE(SUBSTITUTE(DE31,"{会社}",設定!$B$3),"{自分}",設定!$B$4),"{サービス}",設定!$B$5),"{料金}",設定!$B$7),"{日付1}",設定!$B$8),"{日付2}",設定!$B$9),"{時間1}",設定!$B$10),"{時間2}",設定!$B$11),"{時間}","（指定時間）"),"{日付確定}","（確定日）"),"{時間確定}","（確定時間）")) | AC31: =IFERROR(VLOOKUP(DD31,スクリプト_フロー!$A:$F,4,FALSE),"") | AD31: =IF(AC31="","",AC31) | AF31: =IF(DG31="","",SUBSTITUTE(SUBSTITUTE(SUBSTITUTE(SUBSTITUTE(SUBSTITUTE(SUBSTITUTE(SUBSTITUTE(SUBSTITUTE(SUBSTITUTE(SUBSTITUTE(SUBSTITUTE(DG31,"{会社}",設定!$B$3),"{自分}",設定!$B$4),"{サービス}",設定!$B$5),"{料金}",設定!$B$7),"{日付1}",設定!$B$8),"{日付2}",設定!$B$9),"{時間1}",設定!$B$10),"{時間2}",設定!$B$11),"{時間}","（指定時間）"),"{日付確定}","（確定日）"),"{時間確定}","（確定時間）")) | AG31: =IFERROR(VLOOKUP(DF31,スクリプト_フロー!$A:$F,4,FALSE),"") | CZ31: =R31&"|"&S31 -> | | DA31: =IFERROR(VLOOKUP(CZ31,スクリプト_フロー!$A:$F,5,FALSE),"") | DB31: =V31&"|"&W31 -> | | DC31: =IFERROR(VLOOKUP(DB31,スクリプト_フロー!$A:$F,5,FALSE),"") | DD31: =Z31&"|"&AA31 -> | | DE31: =IFERROR(VLOOKUP(DD31,スクリプト_フロー!$A:$F,5,FALSE),"") | DF31: =AD31&"|"&AE31 -> | | DG31: =IFERROR(VLOOKUP(DF31,スクリプト_フロー!$A:$F,5,FALSE),"")
A32: 31 | B32: 大江戸温泉物語 別府清風 | C32: 0570-050-268 | D32: 北浜/別府駅周辺 | G32: ①架電 | I32: =SUBSTITUTE(SUBSTITUTE(SUBSTITUTE(SUBSTITUTE(SUBSTITUTE(SUBSTITUTE(SUBSTITUTE(SUBSTITUTE(SUBSTITUTE(SUBSTITUTE(SUBSTITUTE(Q32,"{会社}",設定!$B$3),"{自分}",設定!$B$4),"{サービス}",設定!$B$5),"{料金}",設定!$B$7),"{日付1}",設定!$B$8),"{日付2}",設定!$B$9),"{時間1}",設定!$B$10),"{時間2}",設定!$B$11),"{時間}","（指定時間）"),"{日付確定}","（確定日）"),"{時間確定}","（確定時間）") | J32: =IFERROR(VLOOKUP(P32,スクリプト_フロー!$A:$F,4,FALSE),"") | K32: 未架電 | P32: =G32&"|"&H32 -> ①架電| | Q32: =IFERROR(VLOOKUP(P32,スクリプト_フロー!$A:$F,5,FALSE),"") | R32: =IF(J32="","",J32) | T32: =IF(DA32="","",SUBSTITUTE(SUBSTITUTE(SUBSTITUTE(SUBSTITUTE(SUBSTITUTE(SUBSTITUTE(SUBSTITUTE(SUBSTITUTE(SUBSTITUTE(SUBSTITUTE(SUBSTITUTE(DA32,"{会社}",設定!$B$3),"{自分}",設定!$B$4),"{サービス}",設定!$B$5),"{料金}",設定!$B$7),"{日付1}",設定!$B$8),"{日付2}",設定!$B$9),"{時間1}",設定!$B$10),"{時間2}",設定!$B$11),"{時間}","（指定時間）"),"{日付確定}","（確定日）"),"{時間確定}","（確定時間）")) | U32: =IFERROR(VLOOKUP(CZ32,スクリプト_フロー!$A:$F,4,FALSE),"") | V32: =IF(U32="","",U32) | X32: =IF(DC32="","",SUBSTITUTE(SUBSTITUTE(SUBSTITUTE(SUBSTITUTE(SUBSTITUTE(SUBSTITUTE(SUBSTITUTE(SUBSTITUTE(SUBSTITUTE(SUBSTITUTE(SUBSTITUTE(DC32,"{会社}",設定!$B$3),"{自分}",設定!$B$4),"{サービス}",設定!$B$5),"{料金}",設定!$B$7),"{日付1}",設定!$B$8),"{日付2}",設定!$B$9),"{時間1}",設定!$B$10),"{時間2}",設定!$B$11),"{時間}","（指定時間）"),"{日付確定}","（確定日）"),"{時間確定}","（確定時間）")) | Y32: =IFERROR(VLOOKUP(DB32,スクリプト_フロー!$A:$F,4,FALSE),"") | Z32: =IF(Y32="","",Y32) | AB32: =IF(DE32="","",SUBSTITUTE(SUBSTITUTE(SUBSTITUTE(SUBSTITUTE(SUBSTITUTE(SUBSTITUTE(SUBSTITUTE(SUBSTITUTE(SUBSTITUTE(SUBSTITUTE(SUBSTITUTE(DE32,"{会社}",設定!$B$3),"{自分}",設定!$B$4),"{サービス}",設定!$B$5),"{料金}",設定!$B$7),"{日付1}",設定!$B$8),"{日付2}",設定!$B$9),"{時間1}",設定!$B$10),"{時間2}",設定!$B$11),"{時間}","（指定時間）"),"{日付確定}","（確定日）"),"{時間確定}","（確定時間）")) | AC32: =IFERROR(VLOOKUP(DD32,スクリプト_フロー!$A:$F,4,FALSE),"") | AD32: =IF(AC32="","",AC32) | AF32: =IF(DG32="","",SUBSTITUTE(SUBSTITUTE(SUBSTITUTE(SUBSTITUTE(SUBSTITUTE(SUBSTITUTE(SUBSTITUTE(SUBSTITUTE(SUBSTITUTE(SUBSTITUTE(SUBSTITUTE(DG32,"{会社}",設定!$B$3),"{自分}",設定!$B$4),"{サービス}",設定!$B$5),"{料金}",設定!$B$7),"{日付1}",設定!$B$8),"{日付2}",設定!$B$9),"{時間1}",設定!$B$10),"{時間2}",設定!$B$11),"{時間}","（指定時間）"),"{日付確定}","（確定日）"),"{時間確定}","（確定時間）")) | AG32: =IFERROR(VLOOKUP(DF32,スクリプト_フロー!$A:$F,4,FALSE),"") | CZ32: =R32&"|"&S32 -> | | DA32: =IFERROR(VLOOKUP(CZ32,スクリプト_フロー!$A:$F,5,FALSE),"") | DB32: =V32&"|"&W32 -> | | DC32: =IFERROR(VLOOKUP(DB32,スクリプト_フロー!$A:$F,5,FALSE),"") | DD32: =Z32&"|"&AA32 -> | | DE32: =IFERROR(VLOOKUP(DD32,スクリプト_フロー!$A:$F,5,FALSE),"") | DF32: =AD32&"|"&AE32 -> | | DG32: =IFERROR(VLOOKUP(DF32,スクリプト_フロー!$A:$F,5,FALSE),"")
... A150: 149 | B150: 別府温泉 旅館 叶屋 | C150: 要確認 | D150: 北浜/別府駅周辺 | G150: ①架電 | I150: =SUBSTITUTE(SUBSTITUTE(SUBSTITUTE(SUBSTITUTE(SUBSTITUTE(SUBSTITUTE(SUBSTITUTE(SUBSTITUTE(SUBSTITUTE(SUBSTITUTE(SUBSTITUTE(Q150,"{会社}",設定!$B$3),"{自分}",設定!$B$4),"{サービス}",設定!$B$5),"{料金}",設定!$B$7),"{日付1}",設定!$B$8),"{日付2}",設定!$B$9),"{時間1}",設定!$B$10),"{時間2}",設定!$B$11),"{時間}","（指定時間）"),"{日付確定}","（確定日）"),"{時間確定}","（確定時間）") | J150: =IFERROR(VLOOKUP(P150,スクリプト_フロー!$A:$F,4,FALSE),"") | K150: 未架電 | P150: =G150&"|"&H150 -> ①架電| | Q150: =IFERROR(VLOOKUP(P150,スクリプト_フロー!$A:$F,5,FALSE),"") | R150: =IF(J150="","",J150) | T150: =IF(DA150="","",SUBSTITUTE(SUBSTITUTE(SUBSTITUTE(SUBSTITUTE(SUBSTITUTE(SUBSTITUTE(SUBSTITUTE(SUBSTITUTE(SUBSTITUTE(SUBSTITUTE(SUBSTITUTE(DA150,"{会社}",設定!$B$3),"{自分}",設定!$B$4),"{サービス}",設定!$B$5),"{料金}",設定!$B$7),"{日付1}",設定!$B$8),"{日付2}",設定!$B$9),"{時間1}",設定!$B$10),"{時間2}",設定!$B$11),"{時間}","（指定時間）"),"{日付確定}","（確定日）"),"{時間確定}","（確定時間）")) | U150: =IFERROR(VLOOKUP(CZ150,スクリプト_フロー!$A:$F,4,FALSE),"") | V150: =IF(U150="","",U150) | X150: =IF(DC150="","",SUBSTITUTE(SUBSTITUTE(SUBSTITUTE(SUBSTITUTE(SUBSTITUTE(SUBSTITUTE(SUBSTITUTE(SUBSTITUTE(SUBSTITUTE(SUBSTITUTE(SUBSTITUTE(DC150,"{会社}",設定!$B$3),"{自分}",設定!$B$4),"{サービス}",設定!$B$5),"{料金}",設定!$B$7),"{日付1}",設定!$B$8),"{日付2}",設定!$B$9),"{時間1}",設定!$B$10),"{時間2}",設定!$B$11),"{時間}","（指定時間）"),"{日付確定}","（確定日）"),"{時間確定}","（確定時間）")) | Y150: =IFERROR(VLOOKUP(DB150,スクリプト_フロー!$A:$F,4,FALSE),"") | Z150: =IF(Y150="","",Y150) | AB150: =IF(DE150="","",SUBSTITUTE(SUBSTITUTE(SUBSTITUTE(SUBSTITUTE(SUBSTITUTE(SUBSTITUTE(SUBSTITUTE(SUBSTITUTE(SUBSTITUTE(SUBSTITUTE(SUBSTITUTE(DE150,"{会社}",設定!$B$3),"{自分}",設定!$B$4),"{サービス}",設定!$B$5),"{料金}",設定!$B$7),"{日付1}",設定!$B$8),"{日付2}",設定!$B$9),"{時間1}",設定!$B$10),"{時間2}",設定!$B$11),"{時間}","（指定時間）"),"{日付確定}","（確定日）"),"{時間確定}","（確定時間）")) | AC150: =IFERROR(VLOOKUP(DD150,スクリプト_フロー!$A:$F,4,FALSE),"") | AD150: =IF(AC150="","",AC150) | AF150: =IF(DG150="","",SUBSTITUTE(SUBSTITUTE(SUBSTITUTE(SUBSTITUTE(SUBSTITUTE(SUBSTITUTE(SUBSTITUTE(SUBSTITUTE(SUBSTITUTE(SUBSTITUTE(SUBSTITUTE(DG150,"{会社}",設定!$B$3),"{自分}",設定!$B$4),"{サービス}",設定!$B$5),"{料金}",設定!$B$7),"{日付1}",設定!$B$8),"{日付2}",設定!$B$9),"{時間1}",設定!$B$10),"{時間2}",設定!$B$11),"{時間}","（指定時間）"),"{日付確定}","（確定日）"),"{時間確定}","（確定時間）")) | AG150: =IFERROR(VLOOKUP(DF150,スクリプト_フロー!$A:$F,4,FALSE),"") | CZ150: =R150&"|"&S150 -> | | DA150: =IFERROR(VLOOKUP(CZ150,スクリプト_フロー!$A:$F,5,FALSE),"") | DB150: =V150&"|"&W150 -> | | DC150: =IFERROR(VLOOKUP(DB150,スクリプト_フロー!$A:$F,5,FALSE),"") | DD150: =Z150&"|"&AA150 -> | | DE150: =IFERROR(VLOOKUP(DD150,スクリプト_フロー!$A:$F,5,FALSE),"") | DF150: =AD150&"|"&AE150 -> | | DG150: =IFERROR(VLOOKUP(DF150,スクリプト_フロー!$A:$F,5,FALSE),"")
A152: 使い方：G列で「現在ステージ」、H列で「相手の反応」を選ぶと、I列に次に話す内容が表示されます。K列で結果ステータスを更新し、L列に次回架電日時、M列にメモを残してください。

Sheet 設定
A1: スクリプト設定（青=入力）
A2: 項目 | B2: 値（入力） | C2: メモ
A3: 会社名 | B3: 株式会社NanoAct
A4: 担当者名（あなた） | B4: キンタマ
A5: サービス名（表示） | B5: 特定小型原付のシェアリング
A6: 対象エリア | B6: 別府市内
A7: 料金（分あたり・円） | B7: 〇〇
A8: 訪問候補日① | B8: 〇月〇日
A9: 訪問候補日② | B9: 〇月〇日
A10: 訪問候補時間① | B10: 〇時〜
A11: 訪問候補時間② | B11: 〇時〜
A12: 資料URL（任意）
A13: 備考 | B13: 事故対応フロー・保険は当社で準備。充電は施設側（充電代負担）。

Sheet スクリプト_フロー
A1: キー | B1: ステージ | C1: 相手の反応（選択） | D1: 次ステージ | E1: 次に話す内容（表示） | F1: 補足
A2: ①架電|受付が出た | B2: ①架電 | C2: 受付が出た | D2: ②受付 | E2: お世話になっております。{会社}の{自分}と申します。別府市内で宿泊者さま向けに「{サービス}」を新たに立ち上げる件で、設置のご相談がありお電話しました。設置や運用のご担当者様（フロント責任者／支配人様など）はいらっしゃいますでしょうか？ | F2: 目的：担当者へ接続
A3: ①架電|担当者に直接繋がった | B3: ①架電 | C3: 担当者に直接繋がった | D3: ⑥目的伝達 | E3: （担当者様へ）お世話になっております。{会社}の{自分}と申します。宿泊者さま向けに「{サービス}」を施設に設置するご相談でお電話しました。今1〜2分だけお時間よろしいでしょうか？
A4: ①架電|自動音声/番号案内 | B4: ①架電 | C4: 自動音声/番号案内 | D4: ①-2自動音声 | E4: （自動音声に従い）『宿泊・フロント』または『総合受付』へ。繋がったら『設置や運用のご担当者様（支配人様など）にお繋ぎいただけますか？』
A5: ①架電|営業時間外 | B5: ①架電 | C5: 営業時間外 | D5: ⑯再架電予定 | E5: 承知しました。営業時間内に改めてお電話いたします。ありがとうございます。失礼いたします。 | F5: 終話
A6: ①-2自動音声|フロント/受付に繋がった | B6: ①-2自動音声 | C6: フロント/受付に繋がった | D6: ②受付 | E6: （繋がったら）お世話になっております。{会社}の{自分}と申します。設置や運用のご担当者様（支配人様など）にお繋ぎいただけますでしょうか？
A7: ①-2自動音声|担当者に繋がった | B7: ①-2自動音声 | C7: 担当者に繋がった | D7: ⑥目的伝達 | E7: （担当者様へ）お世話になっております。{会社}の{自分}と申します。宿泊者さま向けに「{サービス}」を施設に設置するご相談でお電話しました。今1〜2分だけお時間よろしいでしょうか？
A8: ①-2自動音声|繋がらない/切れた | B8: ①-2自動音声 | C8: 繋がらない/切れた | D8: ⑯再架電予定 | E8: 承知しました。改めてお電話いたします。ありがとうございました。失礼いたします。 | F8: 終話
A9: ②受付|担当者に繋いでくれた | B9: ②受付 | C9: 担当者に繋いでくれた | D9: ⑥目的伝達 | E9: （担当者様へ）お世話になっております。{会社}の{自分}と申します。宿泊者さま向けに「{サービス}」を施設に設置するご相談でお電話しました。今1〜2分だけお時間よろしいでしょうか？
A10: ②受付|用件を聞かれた | B10: ②受付 | C10: 用件を聞かれた | D10: ③受付用件 | E10: 宿泊者さま向けに「{サービス}」を施設に設置し、自由に使える仕組みのご提案です。事故時フローと保険、問い合わせ窓口は当社で準備します。ご担当者様に概要だけお伝えしたく、お繋ぎいただけますでしょうか？ | F10: 短く・不安除去
A11: ②受付|担当者不在 | B11: ②受付 | C11: 担当者不在 | D11: ④不在対応 | E11: ありがとうございます。ご担当者様は何時頃がお戻りでしょうか？（繋がりやすいお時間はありますか？）
A12: ②受付|繋げない/NG | B12: ②受付 | C12: 繋げない/NG | D12: ⑤資料送付打診 | E12: 承知しました。負担が出ない形の例と安全面を1枚にまとめた資料があります。よろしければお送りしてもよろしいでしょうか？ | F12: メール取得へ
A13: ③受付用件|担当者に繋いでくれた | B13: ③受付用件 | C13: 担当者に繋いでくれた | D13: ⑥目的伝達 | E13: （担当者様へ）お世話になっております。{会社}の{自分}と申します。宿泊者さま向けに「{サービス}」を施設に設置するご相談でお電話しました。今1〜2分だけお時間よろしいでしょうか？
A14: ③受付用件|担当者不在 | B14: ③受付用件 | C14: 担当者不在 | D14: ④不在対応 | E14: ありがとうございます。ご担当者様は何時頃がお戻りでしょうか？（繋がりやすいお時間はありますか？）
A15: ③受付用件|繋げない/NG | B15: ③受付用件 | C15: 繋げない/NG | D15: ⑤資料送付打診 | E15: 承知しました。概要1枚とQ&A資料があります。よろしければお送りしてもよろしいでしょうか？
A16: ④不在対応|時間指定あり | B16: ④不在対応 | C16: 時間指定あり | D16: ⑯再架電予定 | E16: ありがとうございます。それでは{時間}頃に改めてお電話いたします。お忙しいところありがとうございました。失礼いたします。 | F16: 終話
A17: ④不在対応|時間指定なし | B17: ④不在対応 | C17: 時間指定なし | D17: ⑯再架電予定 | E17: 承知しました。ではまたこちらから改めます。お忙しいところ失礼しました。失礼いたします。 | F17: 終話
A18: ⑤資料送付打診|送付OK（メール取得） | B18: ⑤資料送付打診 | C18: 送付OK（メール取得） | D18: ⑰送付完了 | E18: ありがとうございます。送付先のメールアドレスを伺ってもよろしいでしょうか？ （復唱）ありがとうございます。本日中に資料をお送りします。ご確認後、10分だけご質問のお時間をいただければ幸いです。ありがとうございました。失礼いたします。 | F18: 終話：送付で完結
A19: ⑤資料送付打診|送付NG | B19: ⑤資料送付打診 | C19: 送付NG | D19: ⑱丁寧終了 | E19: 承知しました。お忙しいところ失礼しました。ありがとうございました。失礼いたします。 | F19: 終話
A20: ⑥目的伝達|時間OK | B20: ⑥目的伝達 | C20: 時間OK | D20: ⑦メリット | E20: ありがとうございます。別府市内で宿泊者さま向けに特定小型原付のシェアリング（宿泊者向け貸出）を立ち上げています。設置候補としてご相談したくご連絡しました。ポイントを30秒で3つだけお伝えします。※内容は要検討
A21: ⑥目的伝達|今はNG | B21: ⑥目的伝達 | C21: 今はNG | D21: ⑮日程再調整 | E21: 承知しました。差し支えなければ、改めてお電話するのに都合の良いお時間はございますか？
A22: ⑦メリット|興味あり | B22: ⑦メリット | C22: 興味あり | D22: ⑩ヒアリング | E22: ありがとうございます。ポイントは3つです。①宿泊体験の価値が上がる ②運用負担は最小（保険・窓口は当社） ③設置協力施設様向けに収益分配も検討しています。 まず設置可否の確認をさせてください。1台あたり幅1mほど置けそうなスペースはありますか？
A23: ⑦メリット|費用が気になる | B23: ⑦メリット | C23: 費用が気になる | D23: ⑧費用説明 | E23: 承知しました。費用面だけ先に整理します。
A24: ⑦メリット|安全が気になる | B24: ⑦メリット | C24: 安全が気になる | D24: ⑨安全説明 | E24: 承知しました。安全面のご懸念が一番大事なので先にそこからご説明します。
A25: ⑦メリット|とりあえず資料 | B25: ⑦メリット | C25: とりあえず資料 | D25: ⑤資料送付打診 | E25: 承知しました。概要1枚とQ&Aをお送りします。送付先のメールアドレスを伺ってもよろしいでしょうか？
A26: ⑦メリット|興味なし/NG
A27: ⑧費用説明|説明して続けてOK | B27: ⑧費用説明 | C27: 説明して続けてOK | D27: ⑩ヒアリング | E27: 料金は分あたり{料金}円を想定しています。施設様にお願いするのは、駐輪スペースのご用意と充電（充電代）のご負担です。台数や運用条件によってはSIM費（月3,000〜4,000円/台）をご相談する場合があります。 そのうえで、設置協力施設様向けに収益分配の設計も可能です。 差し支えなければ、施設内で置けそうなスペースはございますか？
A28: ⑧費用説明|それでも難しい | B28: ⑧費用説明 | C28: それでも難しい | D28: ⑱丁寧終了 | E28: 承知しました。費用面が合わない場合は無理にお願いしません。本日はお時間ありがとうございました。失礼いたします。 | F28: 終話
A29: ⑨安全説明|説明して続けてOK | B29: ⑨安全説明 | C29: 説明して続けてOK | D29: ⑩ヒアリング | E29: 事故時の対応フローと保険は当社で準備します。緊急連絡先も当社に一本化し、施設様の現場負担が増えない運用にします。利用ルール（時間帯・走行・返却）も整備します。 差し支えなければ、施設内で置けそうなスペースはございますか？
A30: ⑨安全説明|それでも不安でNG | B30: ⑨安全説明 | C30: それでも不安でNG | D30: ⑱丁寧終了 | E30: 承知しました。安全面のご懸念は当然だと思います。本日はお時間ありがとうございました。失礼いたします。 | F30: 終話
A31: ⑩ヒアリング|スペースあり | B31: ⑩ヒアリング | C31: スペースあり | D31: ⑬クロージング | E31: ありがとうございます。では一度、10分オンラインか、可能であれば15分ほどご訪問で概要をご説明したいのですが、{日付1}{時間1}か{日付2}{時間2}だとどちらがご都合よろしいでしょうか？
A32: ⑩ヒアリング|スペース微妙 | B32: ⑩ヒアリング | C32: スペース微妙 | D32: ⑪代替案 | E32: ありがとうございます。置き場所がネックですよね。屋外の一角でも設置可能で、固定方法も含めて検討できます。置けそうな場所のイメージだけ伺えますか？
A33: ⑩ヒアリング|決裁者確認 | B33: ⑩ヒアリング | C33: 決裁者確認 | D33: ⑫決裁者確認 | E33: ありがとうございます。ご検討いただく場合、最終のご判断はどなたになりますでしょうか？同席が難しければ、資料と短いオンラインで共有も可能です。
A34: ⑩ヒアリング|今は判断できない | B34: ⑩ヒアリング | C34: 今は判断できない | D34: ⑤資料送付打診 | E34: 承知しました。まずは概要資料をお送りしますので、送付先メールを伺ってもよろしいでしょうか？
A35: ⑪代替案|置けそう | B35: ⑪代替案 | C35: 置けそう | D35: ⑬クロージング | E35: ありがとうございます。では条件に合う形で設置方法をこちらで整理します。一度、10分オンラインか15分訪問で概要をご説明したいのですが、{日付1}{時間1}か{日付2}{時間2}だとどちらがご都合よろしいでしょうか？
A36: ⑪代替案|やはり難しい | B36: ⑪代替案 | C36: やはり難しい | D36: ⑱丁寧終了 | E36: 承知しました。置き場所が難しい場合は無理に進めません。本日はありがとうございました。失礼いたします。 | F36: 終話
A37: ⑫決裁者確認|決裁者同席OK | B37: ⑫決裁者確認 | C37: 決裁者同席OK | D37: ⑬クロージング | E37: ありがとうございます。では決裁者様も含めて、10分オンラインか15分訪問で概要をご説明したいのですが、{日付1}{時間1}か{日付2}{時間2}だとどちらがご都合よろしいでしょうか？
A38: ⑫決裁者確認|まず資料で共有 | B38: ⑫決裁者確認 | C38: まず資料で共有 | D38: ⑤資料送付打診 | E38: 承知しました。決裁者様向けの概要資料をお送りします。送付先メールを伺ってもよろしいでしょうか？
A39: ⑬クロージング|日程確定 | B39: ⑬クロージング | C39: 日程確定 | D39: ⑭確定確認 | E39: ありがとうございます。それでは{日付確定}の{時間確定}でお願いします。差し支えなければお名前を伺ってもよろしいでしょうか。住所は（リスト住所）でお間違いないでしょうか？ 当日はよろしくお願いいたします。ありがとうございました。失礼いたします。 | F39: 終話
A40: ⑬クロージング|日程難しい | B40: ⑬クロージング | C40: 日程難しい | D40: ⑮日程再調整 | E40: 承知しました。ではご都合の良い候補日を2つほどいただけますでしょうか？（オンライン10分でも可）
A41: ⑭確定確認|確認完了 | B41: ⑭確定確認 | C41: 確認完了 | D41: ⑱丁寧終了 | E41: ありがとうございます。それでは当日よろしくお願いいたします。失礼いたします。 | F41: 終話
A42: ⑮日程再調整|候補時間もらえた | B42: ⑮日程再調整 | C42: 候補時間もらえた | D42: ⑯再架電予定 | E42: ありがとうございます。それではそのお時間に改めてご連絡いたします。お忙しいところありがとうございました。失礼いたします。 | F42: 終話
A43: ⑮日程再調整|候補もらえない | B43: ⑮日程再調整 | C43: 候補もらえない | D43: ⑯再架電予定 | E43: 承知しました。ではまたこちらから改めます。ありがとうございました。失礼いたします。 | F43: 終話
A44: ⑯再架電予定|架電終了 | B44: ⑯再架電予定 | C44: 架電終了 | D44: ⑱丁寧終了 | E44: （記録用）再架電予定として登録します。 | F44: 内部メモ
A45: ⑰送付完了|送付完了 | B45: ⑰送付完了 | C45: 送付完了 | D45: ⑱丁寧終了 | E45: （記録用）資料送付で完了。 | F45: 内部メモ
A46: ⑱丁寧終了|終了 | B46: ⑱丁寧終了 | C46: 終了 | E46: （完了） | F46: 終話

Sheet 0217
B2: 1) 「提供範囲」の切り分け
B4: 資料上は「車体と管理システムを一気通貫」や「4G×NFCの貸出管理」「GPS追跡/緊急連絡」などが示されています。ここが“どこまで含まれるのか”が全コストに直結します。
B6: 質問：今回の想定（宿泊施設で貸出/返却）で、glafit側が提供するのは何ですか？
B8: ①車体（NFR-01 Pro）
B9: Liteは使えない
B10: ②スマートロック（NFC/IC/アプリ解錠など）
B12: ③管理者ダッシュボード（稼働/売上/故障/位置）
B14: ④ユーザーアプリ（多言語・決済・利用規約同意・緊急連絡）
B16: ⑤サポート窓口（事故/トラブル一次受け）
B17: なし
B18: ⑥GPS追跡・ジオフェンス等（あれば）
B19: 位置情報が分かる
... B130: 「宿泊施設の導入ハードルは“費用と事故不安”なので、保険/事故フロー/緊急窓口のパッケージを前面に出したい（glafit側でテンプレ提供できるか）」

Sheet Sheet1
I1: 6
B2: 15000 | D2: 300000 | F2: 18000 | G2: =F2*I1 -> 108000
B3: 36 | D3: 4000 | F3: 24
B4: =B2*B3 -> 540000 | D4: =D2+(D3*24) -> 396000 | F4: =F2*F3 -> 432000
A5: 下取り

Sheet Sheet2
J11: ↓６台運用して稼働率５％の収支イメージ
B15: ▪️車両＝これ最上位モデル。20万くらいのモデルもあるが以下システム使用不可
B16: ▪️メンテナンス＝おそらく、自前でできるので消耗品交換だけで済むはず
B17: ▪️月額システム使用料＝これの中身は要確認だが前回までの情報では以下の通り
B18: ・スマートロック（NFC/IC/アプリ解錠など）
B19: ・（要確認）管理者ダッシュボード（稼働/売上/故障/位置）
B20: ・ユーザーアプリ（多言語・決済・利用規約同意・緊急連絡）
B21: ・サポート窓口（事故/トラブル一次受け）
B22: ▪️通信料＝ソフトバンク4G

Sheet Q&A
A1: カテゴリ | B1: 質問 | C1: 回答（そのまま読める） | D1: 補足/根拠（URL等） | F1: Q&Aクイック参照
A2: 料金 | B2: 料金はいくら？ | C2: 現在は分あたり{料金}円を想定しており、最終は実証の中で最適化します。宿泊者さまの満足度と回転率のバランスを見て決めます。 | F2: 質問（選択） | G2: 回答（自動）
A3: 費用負担 | B3: 施設側の負担は？ | C3: 施設様にお願いするのは、駐輪スペースのご用意と充電（1回20円程度）です。台数によってはSIM費（月3,000〜4,000円/台）をご相談します（4台以下は不要の想定）。 | G3: =IFERROR(VLOOKUP(F3,$B$2:$C$200,2,FALSE),"")
A4: 安全/事故 | B4: 事故が起きたら？ | C4: 事故時の対応フローと保険は当社で準備します。緊急連絡先も当社に一本化し、施設様の現場負担が増えない運用にします。
A5: 運用 | B5: フロント業務が増えない？ | C5: 基本はアプリで解錠・施錠し、セルフ利用を前提にします。施設様の運用負担を最小化する設計です（必要に応じて運用ルールを調整します）。
A6: 設置 | B6: どれくらいのスペースが必要？ | C6: 目安として1台あたり幅1m程度のスペースがあれば設置可能です。屋内が望ましいですが、屋外でも固定方法を含めて検討できます。
A7: 法令 | B7: 免許やヘルメットは？ | C7: 16歳以上で免許不要です。ヘルメットは努力義務です。車道は20km/h、歩道は条件付きで6km/hなど、法令に沿ったルールで運用します。
A8: 収益 | B8: 収益分配は？ | C8: 設置協力施設様には収益分配の仕組みを用意予定です。台数や稼働に応じた設計なので、条件を伺って提案します。

Sheet リスト
A1: No | B1: ジャンル | C1: 企業名 | D1: 宿泊施設名 | E1: 電話番号 | F1: 住所 | G1: 宿泊単価 | H1: 客層 | I1: 外国人比率 | J1: 駐車場数 | K1: 特徴 | L1: エリア | M1: HP | N1: 情報ソースURL
A2: 1 | B2: ホテル（大型リゾート） | C2: オリックス・ホテルマネジメント株式会社 | D2: 別府温泉 杉乃井ホテル | E2: 0977-78-8888 | F2: 大分県別府市観海寺1 | G2: 概算：¥26,300〜/人（2名1室） | H2: ファミリー・グループ・団体 | I2: 推定：中(10〜25%) | J2: 900 | K2: 大型リゾート／棚湯・水着エリア等が強み。繁忙期の混雑が弱み。 | L2: 観海寺 | M2: https://suginoi.orixhotelsandresorts.com/ | N2: https://suginoi.orixhotelsandresorts.com/ https://www.jalan.net/yad351485/ https://www.ana.co.jp/domtour/booking/csm/search/DSEP0080/init?coptCd=29778
A3: 2 | B3: 温泉旅館（高級） | C3: 株式会社星野リゾート | D3: 界 別府 | E3: 050-3134-8092 | F3: 大分県別府市北浜2-14-29 | G3: 概算：¥44,970〜/人（2名1室） | H3: カップル・記念日・富裕層 | I3: 推定：中〜高(20〜40%) | J3: 32 | K3: 星野リゾートの高級温泉旅館ブランド。上質体験が強み、価格帯高め。 | L3: 北浜 | M3: https://hoshinoresorts.com/ja/hotels/kaibeppu/ | N3: https://hoshinoresorts.com/ja/hotels/kaibeppu/ https://www.jtb.co.jp/kokunai-hotel/htl/8410A70/access/ https://www.jalan.net/yad380307/
A4: 3 | B4: ホテル（温泉・都市型） | C4: アイコニア・ホスピタリティ株式会社 | D4: 亀の井ホテル 別府 | E4: 0977-22-3301 | F4: 大分県別府市中央町5-17 | G4: 概算：¥7,000〜/人 | H4: ファミリー・団体・ビジネス | I4: 推定：中(10〜25%) | J4: 300 | K4: 駅徒歩圏・客室数多めで集客力。団体対応が強み、ピーク時混雑。 | L4: 別府駅周辺 | M4: https://kamenoi-hotels.com/beppu/ | N4: https://kamenoi-hotels.com/beppu/access/ https://www.jalan.net/yad313462/
A5: 4 | B5: ホテル（ビジネス＋温泉） | C5: 株式会社西鉄ホテルズ | D5: 西鉄リゾートイン別府 | E5: 0977-26-5151 | F5: 大分県別府市北浜2-10-4 | G5: 概算：¥6,700〜/人 | H5: ビジネス・観光（カップル/友人） | I5: 推定：中(10〜25%) | J5: 38 | K5: 北浜バス停至近・温泉大浴場。立地強み、駐車場台数は限定。 | L5: 北浜 | M5: https://inn-beppu.nnr-h.com/ | N5: https://travel.rakuten.co.jp/HOTEL/16660/16660.html https://inn-beppu.nnr-h.com/ https://onsendo.beppu-navi.jp/y132/
A6: 5 | B6: 旅館（ハイクラス） | C6: つるみ観光株式会社 | D6: 別府温泉 ホテル白菊 | E6: 0977-21-2111 | F6: 大分県別府市上田の湯町16-36 | G6: 概算：¥20,000〜/人（2名1室） | H6: カップル・ファミリー・シニア | I6: 推定：低〜中(5〜15%) | J6: 70 | K6: 老舗の上質旅館。料理・接客が強み。建物の古さは好みが分かれる可能性。 | L6: 駅周辺 | M6: https://www.shiragiku.co.jp/ | N6: https://onsendo.beppu-navi.jp/y116/ https://www.shiragiku.co.jp/ https://www.buffett-code.com/company/df78lrmx6j/
A7: 6 | B7: 旅館（女性人気） | C7: ＪＲ九州ホテルズアンドリゾーツ株式会社 | D7: 竹と椿のお宿 花べっぷ | E7: 0977-21-0050 | F7: 大分県別府市北浜3-14-29 | G7: 概算：¥25,500〜/人（2名1室） | H7: 女性旅・カップル | I7: 推定：中(10〜25%) | J7: 15 | K7: JR九州系。デザイン性・駅近が強み。駐車場は少なめ。 | L7: 北浜 | M7: https://hana-beppu.jp/ | N7: https://www.jalan.net/yad339944/ https://onsendo.beppu-navi.jp/y25/
A8: 7 | B8: 旅館（鉄輪温泉） | C8: 合資会社 鬼山地獄 | D8: おにやまホテル | E8: 0977-66-1121 | F8: 大分県別府市鉄輪335-1 | G8: 概算：¥15,000〜/人 | H8: ファミリー・観光客（地獄めぐり） | I8: 推定：中(10〜25%) | J8: 50 | K8: 地獄めぐり至近・展望露天風呂。観光動線が強み。坂道エリア。 | L8: 鉄輪 | M8: https://www.oniyama-hotel.co.jp/ | N8: https://www.oniyama-hotel.co.jp/ https://www.sorin-oita.or.jp/Sorin/Servlet?bn=companyguide&companyNo=44022027241&proc=detail https://www.aeoncompass.com/hotel/access/4424002019
A9: 8 | B9: ホテル（和風・温泉） | C9: 株式会社共立メンテナンス | D9: 別府八湯 御宿 野乃別府 | E9: 0977-21-5489 | F9: 大分県別府市駅前本町2-6 | G9: 概算：¥7,125〜/人 | H9: ビジネス・カップル・1人旅 | I9: 推定：中(10〜25%) | J9: 102 | K9: 駅徒歩1分・貸切風呂/サウナ等が強み。人気で満室になりやすい。 | L9: 別府駅周辺 | M9: https://dormy-hotels.com/dormyinn/hotels/nono_beppu/ | N9: https://dormy-hotels.com/dormyinn/hotels/nono_beppu/access/ https://www.jalan.net/yad368537/plan/
A10: 9 | B10: ホテル（都市型・温泉） | C10: 株式会社アマネク | D10: アマネク別府ゆらり | E10: 0977-76-5566 | F10: 大分県別府市駅前本町6-35 | G10: 概算：¥7,835〜/人 | H10: 観光・ビジネス・若年層 | I10: 推定：中〜高(15〜35%) | J10: 提携（台数要確認） | K10: 駅近・ルーフトップ/大浴場等が強み。自前Pなしで提携運用。 | L10: 別府駅周辺 | M10: https://amanekhotels.jp/beppu/ | N10: https://amanekhotels.jp/beppu/ https://www.jalan.net/yad383751/plan/ https://amanekhotels.jp/beppu/access/images/parking-guide.pdf
A11: 10 | B11: ホテル（ビジネス） | C11: 株式会社アマネク | D11: アマネクイン別府 | E11: 0977-76-5565 | F11: 大分県別府市駅前本町6-28 | G11: 概算：¥6,500〜/人 | H11: ビジネス・出張・素泊まり | I11: 推定：中(10〜25%) | J11: 提携（台数要確認） | K11: 駅近・コスパ重視。長期滞在にも。温泉設備は限定的。 | L11: 別府駅周辺 | M11: https://amanekhotels.jp/beppu/ | N11: https://amanekhotels.jp/beppu/ https://amanekhotels.jp/beppu/access/images/parking-guide.pdf
A12: 11 | B12: ホテル（ブティック・温泉） | C12: 株式会社FKS | D12: MURE Beppu | E12: 0977-23-3377 | F12: 大分県別府市楠町19-15 | G12: 概算：¥12,000〜/人 | H12: カップル・友人・小規模旅行 | I12: 推定：中(10〜25%) | J12: 14 | K12: モダンデザイン×温泉。客室数少で体験品質高。繁忙期は在庫少。 | L12: 楠町（ゆめタウン周辺） | M12: https://www.mure-beppu.com/ | N12: https://barifuri-oita.com/spot/75157/ https://tp.furunavi.jp/Plan/Detail?plId=8646 https://www.buffett-code.com/company/nri9xhvge6/
A13: 12 | B13: ホテル（オーシャンビュー） | C13: （要確認） | D13: REX HOTEL別府 | E13: 0977-23-6111 | F13: 大分県別府市若草町13-21 | G13: 概算：¥21,250〜/人（2名1室） | H13: カップル・ファミリー | I13: 推定：低〜中(5〜15%) | J13: 46 | K13: 全室オーシャンフロント。景観が強み。中心街からやや離れ。 | L13: 若草・餅ヶ浜 | M13: https://rexhotel-beppu.co.jp/ | N13: https://www.aeoncompass.com/hotel/access/4424002018 https://www.jalan.net/yad353158/
... A30: 29 | B30: 旅館（ハイクラス） | C30: （要確認） | D30: ホテルうみね | E30: 0977-26-0002 | F30: 大分県別府市北浜3-8-3 | G30: 概算：¥49,750〜/人 | H30: カップル・大人旅・記念日 | I30: 推定：中(10〜25%) | J30: 要確認 | K30: 全室半露天風呂付き等のプライベート感が強み。価格帯高め。 | L30: 北浜 | M30: https://umine.jp/ | N30: https://map.yahoo.co.jp/v3/place/Wg0F_nKQWcE https://www.kayak.co.jp/%E5%88%A5%E5%BA%9C%E5%B8%82-%E3%83%9B%E3%83%86%E3%83%AB-%E3%83%9B%E3%83%86%E3%83%AB%E3%81%86%E3%81%BF%E3%81%AD.624843.ksp https://umine.jp/
A31: 30 | B31: ホテル | C31: 要確認 | D31: 海薫る宿ホテルニュー松実 | E31: 0977-23-2201 | F31: 大分県別府市北浜3丁目14-8 | G31: 要確認 | H31: 要確認 | I31: 要確認 | J31: 要確認 | K31: 別府市旅館ホテル組合掲載（連絡先あり） | L31: 北浜/別府駅周辺 | M31: 要確認
A32: 31 | B32: ホテル | C32: 大江戸温泉物語 | D32: 大江戸温泉物語 別府清風 | E32: 0570-050-268 | F32: 大分県別府市北浜2-12-21 | G32: 要確認 | H32: 要確認 | I32: 要確認 | J32: 要確認 | K32: 別府市旅館ホテル組合掲載（連絡先あり） | L32: 北浜/別府駅周辺 | M32: 要確認
A33: 32 | B33: 旅館 | C33: 要確認 | D33: 喜可久旅館 | E33: 0977-75-8730 | F33: 大分県別府市楠町7-9 | G33: 要確認 | H33: 要確認 | I33: 要確認 | J33: 要確認 | K33: 別府市旅館ホテル組合掲載（連絡先あり） | L33: 楠町/別府駅周辺 | M33: 要確認
A34: 33 | B34: 旅館 | C34: 要確認 | D34: 匠晴の宿心庵 | E34: 0977-75-8400 | F34: 大分県別府市弓ヶ浜町3番10号 | G34: 要確認 | H34: 要確認 | I34: 要確認 | J34: 要確認 | K34: 別府市旅館ホテル組合掲載（連絡先あり） | L34: 北浜/別府駅周辺 | M34: 要確認
A35: 34 | B35: ホテル | C35: 要確認 | D35: グッドイン別府 | E35: 0977-22-3001 | F35: 大分県別府市浜町10番 | G35: 要確認 | H35: 要確認 | I35: 要確認 | J35: 要確認 | K35: 別府市旅館ホテル組合掲載（連絡先あり） | L35: 浜町/別府駅周辺 | M35: 要確認
A36: 35 | B36: 旅館 | C36: 要確認 | D36: くつろぎの宿山田別荘 | E36: 0977-24-2121 | F36: 大分県別府市北浜3丁目2-18 | G36: 要確認 | H36: 要確認 | I36: 要確認 | J36: 要確認 | K36: 別府市旅館ホテル組合掲載（連絡先あり） | L36: 北浜/別府駅周辺 | M36: 要確認
A37: 36 | B37: ホテル | C37: 要確認 | D37: シーサイドホテル美松 大江亭 | E37: 0977-23-4301 | F37: 大分県別府市北浜3丁目14-17 | G37: 要確認 | H37: 要確認 | I37: 要確認 | J37: 要確認 | K37: 別府市旅館ホテル組合掲載（連絡先あり） | L37: 北浜/別府駅周辺 | M37: 要確認
A38: 37 | B38: 旅館 | C38: 要確認 | D38: 旅のお宿臨海 | E38: 0977-22-3361 | F38: 大分県別府市北浜3丁目10-15 | G38: 要確認 | H38: 要確認 | I38: 要確認 | J38: 要確認 | K38: 別府市旅館ホテル組合掲載（連絡先あり） | L38: 北浜/別府駅周辺 | M38: 要確認
A39: 38 | B39: 旅館 | C39: 要確認 | D39: 天空湯房清海荘 | E39: 0977-22-0275 | F39: 大分県別府市北浜3丁目14-3 | G39: 要確認 | H39: 要確認 | I39: 要確認 | J39: 要確認 | K39: 別府市旅館ホテル組合掲載（連絡先あり） | L39: 北浜/別府駅周辺 | M39: 要確認
A40: 39 | B40: ホテル | C40: 要確認 | D40: ビジネス観光ホテルなぎさ | E40: 0977-23-8101 | F40: 大分県別府市北浜3丁目10-10 | G40: 要確認 | H40: 要確認 | I40: 要確認 | J40: 要確認 | K40: 別府市旅館ホテル組合掲載（連絡先あり） | L40: 北浜/別府駅周辺 | M40: 要確認
A41: 40 | B41: 旅館 | C41: 要確認 | D41: べっぷ好楽 | E41: 0977-22-1331 | F41: 大分県別府市北浜3丁目13-21 | G41: 要確認 | H41: 要確認 | I41: 要確認 | J41: 要確認 | K41: 別府市旅館ホテル組合掲載（連絡先あり） | L41: 北浜/別府駅周辺 | M41: 要確認
A42: 41 | B42: 旅館 | C42: 要確認 | D42: 別府のお宿加賀屋 | E42: 0977-75-7224 | F42: 大分県別府市北浜3丁目12-14 | G42: 要確認 | H42: 要確認 | I42: 要確認 | J42: 要確認 | K42: 別府市旅館ホテル組合掲載（連絡先あり） | L42: 北浜/別府駅周辺 | M42: 要確認
... A150: 149 | B150: 旅館 | C150: 要確認 | D150: 別府温泉 旅館 叶屋 | E150: 要確認 | F150: 大分県別府市北浜 | G150: 要確認 | H150: 要確認 | I150: 要確認 | J150: 要確認 | K150: 追加候補（要確認項目あり） | L150: 北浜/別府駅周辺 | M150: 要確認

Sheet リスト_依存プルダウン
A1: ①架電 | B1: ①-2自動音声 | C1: ②受付 | D1: ③受付用件 | E1: ④不在対応 | F1: ⑤資料送付打診 | G1: ⑥目的伝達 | H1: ⑦メリット | I1: ⑧費用説明 | J1: ⑨安全説明 | K1: ⑩ヒアリング | L1: ⑪代替案 | M1: ⑫決裁者確認 | N1: ⑬クロージング | O1: ⑭確定確認 | P1: ⑮日程再調整 | Q1: ⑯再架電予定 | R1: ⑰送付完了 | S1: ⑱丁寧終了
A2: 受付が出た | B2: フロント/受付に繋がった | C2: 担当者に繋いでくれた | D2: 担当者に繋いでくれた | E2: 時間指定あり | F2: 送付NG | G2: 今はNG | H2: とりあえず資料 | I2: それでも難しい | J2: それでも不安でNG | K2: スペースあり | L2: やはり難しい | M2: まず資料で共有 | N2: 日程確定 | O2: 確認完了 | P2: 候補もらえない | Q2: 架電終了 | R2: 送付完了 | S2: 終了
A3: 営業時間外 | B3: 担当者に繋がった | C3: 担当者不在 | D3: 担当者不在 | E3: 時間指定なし | F3: 送付OK（メール取得） | G3: 時間OK | H3: 安全が気になる | I3: 説明して続けてOK | J3: 説明して続けてOK | K3: スペース微妙 | L3: 置けそう | M3: 決裁者同席OK | N3: 日程難しい | P3: 候補時間もらえた
A4: 担当者に直接繋がった | B4: 繋がらない/切れた | C4: 用件を聞かれた | D4: 繋げない/NG | H4: 興味あり | K4: 今は判断できない
A5: 自動音声/番号案内 | C5: 繋げない/NG | H5: 興味なし/NG | K5: 決裁者確認
H6: 費用が気になる

Sheet 内部_リスト
A1: STAGE_LIST | B1: STATUS_LIST | C1: MAP_STAGE | D1: MAP_RANGE | F1: ①-2自動音声 | G1: ①架電 | H1: ②受付 | I1: ③受付用件 | J1: ④不在対応 | K1: ⑤資料送付打診 | L1: ⑥目的伝達 | M1: ⑦メリット | N1: ⑧費用説明 | O1: ⑨安全説明 | P1: ⑩ヒアリング | Q1: ⑪代替案 | R1: ⑫決裁者確認 | S1: ⑬クロージング | T1: ⑭確定確認 | U1: ⑮日程再調整 | V1: ⑯再架電予定 | W1: ⑰送付完了 | X1: ⑱丁寧終了
A2: ①-2自動音声 | B2: 未架電 | C2: ①-2自動音声 | D2: RESPX_001 | F2: フロント/受付に繋がった | G2: 受付が出た | H2: 担当者に繋いでくれた | I2: 担当者に繋いでくれた | J2: 時間指定あり | K2: 送付NG | L2: 今はNG | M2: とりあえず資料 | N2: それでも難しい | O2: それでも不安でNG | P2: スペースあり | Q2: やはり難しい | R2: まず資料で共有 | S2: 日程確定 | T2: 確認完了 | U2: 候補もらえない | V2: 架電終了 | W2: 送付完了 | X2: 終了
A3: ①架電 | B3: 折返し待ち | C3: ①架電 | D3: RESPX_002 | F3: 担当者に繋がった | G3: 営業時間外 | H3: 担当者不在 | I3: 担当者不在 | J3: 時間指定なし | K3: 送付OK（メール取得） | L3: 時間OK | M3: 安全が気になる | N3: 説明して続けてOK | O3: 説明して続けてOK | P3: スペース微妙 | Q3: 置けそう | R3: 決裁者同席OK | S3: 日程難しい | U3: 候補時間もらえた
A4: ②受付 | B4: 再架電予定 | C4: ②受付 | D4: RESPX_003 | F4: 繋がらない/切れた | G4: 担当者に直接繋がった | H4: 用件を聞かれた | I4: 繋げない/NG | M4: 興味あり | P4: 今は判断できない
A5: ③受付用件 | B5: 資料送付 | C5: ③受付用件 | D5: RESPX_004 | G5: 自動音声/番号案内 | H5: 繋げない/NG | M5: 費用が気になる | P5: 決裁者確認
A6: ④不在対応 | B6: 訪問/MTG確定 | C6: ④不在対応 | D6: RESPX_005
A7: ⑤資料送付打診 | B7: NG | C7: ⑤資料送付打診 | D7: RESPX_006
A8: ⑥目的伝達 | B8: 保留 | C8: ⑥目的伝達 | D8: RESPX_007
A9: ⑦メリット | B9: 完了 | C9: ⑦メリット | D9: RESPX_008
A10: ⑧費用説明 | C10: ⑧費用説明 | D10: RESPX_009
A11: ⑨安全説明 | C11: ⑨安全説明 | D11: RESPX_010
A12: ⑩ヒアリング | C12: ⑩ヒアリング | D12: RESPX_011
A13: ⑪代替案 | C13: ⑪代替案 | D13: RESPX_012
A14: ⑫決裁者確認 | C14: ⑫決裁者確認 | D14: RESPX_013
A15: ⑬クロージング | C15: ⑬クロージング | D15: RESPX_014
A16: ⑭確定確認 | C16: ⑭確定確認 | D16: RESPX_015
A17: ⑮日程再調整 | C17: ⑮日程再調整 | D17: RESPX_016
A18: ⑯再架電予定 | C18: ⑯再架電予定 | D18: RESPX_017
A19: ⑰送付完了 | C19: ⑰送付完了 | D19: RESPX_018
A20: ⑱丁寧終了 | C20: ⑱丁寧終了 | D20: RESPX_019
